{
    "results": [
        {
            "id": "25027574",
            "Retailer": "DeadEye Precision",
            "Description": "26 Nosler Trophy Grade 129g ABLR 8rds Save $ Send us your brass! We can make this ammo for you!",
            "Brand": "Nosler",
            "Caliber": "Nosler",
            "Grains": null,
            "Price": 12.0,
            "Rounds": 8,
            "Casing": "brass",
            "S/H": "7",
            "Limits": "N/A",
            "New?": "new",
            "$/round": 1.5,
            "Link": "https://ammoseek.com/share/a/275492731426"
        },
        {
            "id": "11879221",
            "Retailer": "Foundry Outdoors",
            "Description": "Nosler 40302 E-Tip Hunting 26 Nosler 120 GR E-Tip 20 Bx/ 10 Cs 054041403023",
            "Brand": "Nosler",
            "Caliber": "Nosler",
            "Grains": 120,
            "Price": 41.11,
            "Rounds": 20,
            "Casing": "brass",
            "S/H": "4",
            "Limits": "N/A",
            "New?": "new",
            "$/round": 2.06,
            "Link": "https://ammoseek.com/share/a/258408043684"
        },
        {
            "id": "15871389",
            "Retailer": "Fast Ammo",
            "Description": "NOSLER 26 NOSLER 140GR BALLISTIC TIP 20RD 10BX/CS 054041434591",
            "Brand": "Nosler",
            "Caliber": "Nosler",
            "Grains": 140,
            "Price": 41.4,
            "Rounds": 20,
            "Casing": "brass",
            "S/H": "3",
            "Limits": "N/A",
            "New?": "new",
            "$/round": 2.07,
            "Link": "https://ammoseek.com/share/a/274704638050"
        },
        {
            "id": "33005909",
            "Retailer": "Fast Ammo",
            "Description": "NOSLER 26 NOSLER 140GR BALLISTIC TIP 20RD 10BX/CS 054041434591",
            "Brand": "Nosler",
            "Caliber": "Nosler",
            "Grains": 140,
            "Price": 207.0,
            "Rounds": 100,
            "Casing": "brass",
            "S/H": "3",
            "Limits": "N/A",
            "New?": "new",
            "$/round": 2.07,
            "Link": "https://ammoseek.com/share/a/274704638053"
        },
        {
            "id": "27408087",
            "Retailer": "Fast Ammo",
            "Description": "NOSLER 26 NOSLER 140GR BALLISTIC TIP 20RD 10BX/CS 054041434591",
            "Brand": "Nosler",
            "Caliber": "Nosler",
            "Grains": 140,
            "Price": 414.0,
            "Rounds": 200,
            "Casing": "brass",
            "S/H": "3",
            "Limits": "N/A",
            "New?": "new",
            "$/round": 2.07,
            "Link": "https://ammoseek.com/share/a/274704638056"
        },
        {
            "id": "22014630",
            "Retailer": "Ammo ASAP",
            "Description": "NOSLER 26 NOSLER 140GR BALLISTIC TIP 20RD 10BX/CS 054041434591",
            "Brand": "Nosler",
            "Caliber": "Nosler",
            "Grains": 140,
            "Price": 41.44,
            "Rounds": 20,
            "Casing": "brass",
            "S/H": "3",
            "Limits": "N/A",
            "New?": "new",
            "$/round": 2.07,
            "Link": "https://ammoseek.com/share/a/288124254529"
        },
        {
            "id": "24561584",
            "Retailer": "Ammo ASAP",
            "Description": "NOSLER 26 NOSLER 140GR BALLISTIC TIP 20RD 10BX/CS 054041434591",
            "Brand": "Nosler",
            "Caliber": "Nosler",
            "Grains": 140,
            "Price": 207.2,
            "Rounds": 100,
            "Casing": "brass",
            "S/H": "3",
            "Limits": "N/A",
            "New?": "new",
            "$/round": 2.07,
            "Link": "https://ammoseek.com/share/a/288124254517"
        },
        {
            "id": "14948576",
            "Retailer": "Ammo ASAP",
            "Description": "NOSLER 26 NOSLER 140GR BALLISTIC TIP 20RD 10BX/CS 054041434591",
            "Brand": "Nosler",
            "Caliber": "Nosler",
            "Grains": 140,
            "Price": 414.4,
            "Rounds": 200,
            "Casing": "brass",
            "S/H": "3",
            "Limits": "N/A",
            "New?": "new",
            "$/round": 2.07,
            "Link": "https://ammoseek.com/share/a/288124254502"
        },
        {
            "id": "16558954",
            "Retailer": "USA Gun Store",
            "Description": "NOSLER BT 26 NOSLER 140GR 054041434591",
            "Brand": "Nosler",
            "Caliber": "Nosler",
            "Grains": 140,
            "Price": 41.99,
            "Rounds": 20,
            "Casing": "brass",
            "S/H": "9",
            "Limits": "N/A",
            "New?": "new",
            "$/round": 2.1,
            "Link": "https://ammoseek.com/share/a/257891169283"
        },
        {
            "id": "13350855",
            "Retailer": "GrabAGun",
            "Description": "Nosler Trophy Grade Brass .26 Nosler 140-Grain 20-Rounds BTIP - $12.99 Shipping on Unlimited Boxes - UPC: 054041434591",
            "Brand": "Nosler",
            "Caliber": "Nosler",
            "Grains": 140,
            "Price": 43.09,
            "Rounds": 20,
            "Casing": "brass",
            "S/H": "8",
            "Limits": "N/A",
            "New?": "new",
            "$/round": 2.15,
            "Link": "https://ammoseek.com/share/a/243467332153"
        },
        {
            "id": "29012404",
            "Retailer": "Armed In Michigan",
            "Description": "Nosler Ammo BT-26 Nosler 140gr BT (20ct) 054041434591",
            "Brand": "Nosler",
            "Caliber": "Nosler",
            "Grains": 140,
            "Price": 43.99,
            "Rounds": 20,
            "Casing": "brass",
            "S/H": "8",
            "Limits": "N/A",
            "New?": "new",
            "$/round": 2.2,
            "Link": "https://ammoseek.com/share/a/295256816389"
        },
        {
            "id": "66205367",
            "Retailer": "Rivertown Munitions",
            "Description": "Nosler 26 Nosler 140 grain Ballistic Tip BT 140 grain Hunting Ammunition (20 rd box)",
            "Brand": "Nosler",
            "Caliber": "Nosler",
            "Grains": 140,
            "Price": 44.0,
            "Rounds": 20,
            "Casing": "brass",
            "S/H": "8",
            "Limits": "N/A",
            "New?": "new",
            "$/round": 2.2,
            "Link": "https://ammoseek.com/share/a/243525144616"
        },
        {
            "id": "19371512",
            "Retailer": "Outdoor Limited",
            "Description": "Nosler 26 Nosler Ammunition NOS43459 140 Grain Ballistic Tip 20 Rounds 054041434591FREE SHIPPING on orders $200+",
            "Brand": "Nosler",
            "Caliber": "Nosler",
            "Grains": 140,
            "Price": 44.99,
            "Rounds": 20,
            "Casing": "brass",
            "S/H": "7CF",
            "Limits": "N/A",
            "New?": "new",
            "$/round": 2.25,
            "Link": "https://ammoseek.com/share/a/303090384490"
        },
        {
            "id": "97123547",
            "Retailer": "Big Mike's Guns and Ammo",
            "Description": "NOS AMMO 26NOS 140GR BT 20/10 054041434591",
            "Brand": "Nosler",
            "Caliber": "Nosler",
            "Grains": 140,
            "Price": 45.0,
            "Rounds": 20,
            "Casing": "brass",
            "S/H": "9",
            "Limits": "N/A",
            "New?": "new",
            "$/round": 2.25,
            "Link": "https://ammoseek.com/share/a/285208210678"
        },
        {
            "id": "84779709",
            "Retailer": "Sentry Ammo",
            "Description": "NOSLER 26 NOSLER 140GR BALLISTIC TIP 20RD 10BX/CS 054041434591",
            "Brand": "Nosler",
            "Caliber": "Nosler",
            "Grains": 140,
            "Price": 455.53,
            "Rounds": 200,
            "Casing": "brass",
            "S/H": "5",
            "Limits": "N/A",
            "New?": "new",
            "$/round": 2.28,
            "Link": "https://ammoseek.com/share/a/275879309563"
        },
        {
            "id": "18773080",
            "Retailer": "Shooting Surplus",
            "Description": "Nosler Ballistic Tip Rifle Ammunition 26 Nosler 140 gr. BT SP 20 rd. 054041434591",
            "Brand": "Nosler",
            "Caliber": "Nosler",
            "Grains": 140,
            "Price": 45.88,
            "Rounds": 20,
            "Casing": "brass",
            "S/H": "8",
            "Limits": "N/A",
            "New?": "new",
            "$/round": 2.29,
            "Link": "https://ammoseek.com/share/a/293798982139"
        },
        {
            "id": "13502582",
            "Retailer": "Sentry Ammo",
            "Description": "NOSLER 26 NOSLER 140GR BALLISTIC TIP 20RD 10BX/CS 054041434591",
            "Brand": "Nosler",
            "Caliber": "Nosler",
            "Grains": 140,
            "Price": 45.92,
            "Rounds": 20,
            "Casing": "brass",
            "S/H": "5",
            "Limits": "N/A",
            "New?": "new",
            "$/round": 2.3,
            "Link": "https://ammoseek.com/share/a/275879309533"
        },
        {
            "id": "15817219",
            "Retailer": "Sentry Ammo",
            "Description": "NOSLER 26 NOSLER 140GR BALLISTIC TIP 20RD 10BX/CS 054041434591",
            "Brand": "Nosler",
            "Caliber": "Nosler",
            "Grains": 140,
            "Price": 229.67,
            "Rounds": 100,
            "Casing": "brass",
            "S/H": "5",
            "Limits": "N/A",
            "New?": "new",
            "$/round": 2.3,
            "Link": "https://ammoseek.com/share/a/275879309551"
        },
        {
            "id": "99390587",
            "Retailer": "Natchez Shooting & Outdoors",
            "Description": "Nosler Ammo BT-26 Nosler 140gr BT (20ct) 054041434591",
            "Brand": "Nosler",
            "Caliber": "Nosler",
            "Grains": 140,
            "Price": 45.99,
            "Rounds": 20,
            "Casing": "brass",
            "S/H": "5",
            "Limits": "N/A",
            "New?": "new",
            "$/round": 2.3,
            "Link": "https://ammoseek.com/share/a/243474747916"
        },
        {
            "id": "10111521",
            "Retailer": "Gman Sporting Arms",
            "Description": "Nosler 51288 Match Grade 26 Nosler 140 gr Custom Competition 20 Bx/ 10 Cs 054041512886",
            "Brand": "Nosler",
            "Caliber": "Nosler",
            "Grains": 140,
            "Price": 46.0,
            "Rounds": 20,
            "Casing": "brass",
            "S/H": "3",
            "Limits": "N/A",
            "New?": "new",
            "$/round": 2.3,
            "Link": "https://ammoseek.com/share/a/243598939609"
        },
        {
            "id": "26552329",
            "Retailer": "Black Basin",
            "Description": "NOSLER 26 NOSLER 140GR BALLISTIC TIP 20RD 10BX/CS 054041434591FREE SHIPPING on orders over $500",
            "Brand": "Nosler",
            "Caliber": "Nosler",
            "Grains": 140,
            "Price": 463.57,
            "Rounds": 200,
            "Casing": "brass",
            "S/H": "9CF",
            "Limits": "N/A",
            "New?": "new",
            "$/round": 2.32,
            "Link": "https://ammoseek.com/share/a/310974802591"
        },
        {
            "id": "66062020",
            "Retailer": "Ammo Hero",
            "Description": "NOSLER 26 NOSLER 140GR BALLISTIC TIP 20RD 10BX/CS 054041434591FREE SHIPPING",
            "Brand": "Nosler",
            "Caliber": "Nosler",
            "Grains": 140,
            "Price": 463.57,
            "Rounds": 200,
            "Casing": "brass",
            "S/H": "F",
            "Limits": "N/A",
            "New?": "new",
            "$/round": 2.32,
            "Link": "https://ammoseek.com/share/a/276142397521"
        },
        {
            "id": "20942767",
            "Retailer": "Ammunition Depot",
            "Description": "Nosler E-tip 26 Nosler 120 Grain E-Tip Lead-Free (20 Rounds) 054041403023FREE SHIPPING on orders over $149",
            "Brand": "Nosler",
            "Caliber": "Nosler",
            "Grains": 120,
            "Price": 46.49,
            "Rounds": 20,
            "Casing": "brass",
            "S/H": "8CF",
            "Limits": "N/A",
            "New?": "new",
            "$/round": 2.33,
            "Link": "https://ammoseek.com/share/a/254502789313"
        },
        {
            "id": "10001015",
            "Retailer": "US Armory",
            "Description": "Nosler Ballistic Tip 054041434591 26 Nosler 140 Grains Ballistic Tip",
            "Brand": "Nosler",
            "Caliber": "Nosler",
            "Grains": 140,
            "Price": 46.99,
            "Rounds": 20,
            "Casing": "brass",
            "S/H": "4",
            "Limits": "N/A",
            "New?": "new",
            "$/round": 2.35,
            "Link": "https://ammoseek.com/share/a/279191743051"
        },
        {
            "id": "26931941",
            "Retailer": "Armored Boar Gunworks",
            "Description": "Nosler Ammo BT-26 Nosler 140gr BT (20ct) 054041434591",
            "Brand": "Nosler",
            "Caliber": "Nosler",
            "Grains": 140,
            "Price": 47.0,
            "Rounds": 20,
            "Casing": "brass",
            "S/H": "8",
            "Limits": "N/A",
            "New?": "new",
            "$/round": 2.35,
            "Link": "https://ammoseek.com/share/a/298320395743"
        },
        {
            "id": "39811333",
            "Retailer": "Paramount Defense LLC",
            "Description": "Nosler Ammo BT-26 Nosler 140gr BT (20ct) 054041434591",
            "Brand": "Nosler",
            "Caliber": "Nosler",
            "Grains": 140,
            "Price": 47.0,
            "Rounds": 20,
            "Casing": "brass",
            "S/H": "8",
            "Limits": "N/A",
            "New?": "new",
            "$/round": 2.35,
            "Link": "https://ammoseek.com/share/a/311600495161"
        },
        {
            "id": "18011853",
            "Retailer": "MCM Tactical",
            "Description": "Nosler Ammo BT-26 Nosler 140gr BT (20ct) 054041434591",
            "Brand": "Nosler",
            "Caliber": "Nosler",
            "Grains": 140,
            "Price": 47.32,
            "Rounds": 20,
            "Casing": "brass",
            "S/H": "8",
            "Limits": "N/A",
            "New?": "new",
            "$/round": 2.37,
            "Link": "https://ammoseek.com/share/a/272882854570"
        },
        {
            "id": "24338724",
            "Retailer": "LG Outdoors",
            "Description": "Nosler Ballistic Tip Rifle Ammunition 26 Nosler 140 gr. BT SP 20 rd. Model: 43459(Price per unit for order of 10+ units)054041434591",
            "Brand": "Nosler",
            "Caliber": "Nosler",
            "Grains": 140,
            "Price": 47.39,
            "Rounds": 20,
            "Casing": "brass",
            "S/H": "5",
            "Limits": "N/A",
            "New?": "new",
            "$/round": 2.37,
            "Link": "https://ammoseek.com/share/a/255483772807"
        },
        {
            "id": "24723782",
            "Retailer": "Ammo Sale",
            "Description": "Nosler Ballistic Tip Rifle Ammunition 26 Nosler 140 gr. BT SP 20 rd. Model: 43459(Price per unit for order of 10+ units)054041434591",
            "Brand": "Nosler",
            "Caliber": "Nosler",
            "Grains": 140,
            "Price": 47.39,
            "Rounds": 20,
            "Casing": "brass",
            "S/H": "5",
            "Limits": "N/A",
            "New?": "new",
            "$/round": 2.37,
            "Link": "https://ammoseek.com/share/a/255483090118"
        },
        {
            "id": "18361954",
            "Retailer": "Wholesale Hunter",
            "Description": "Nosler BT 26 Nosler 140Gr Ballistic Tip 20Rd 10Bx/Cs Case of 200 054041434591(price reflects 5% bulk discount)",
            "Brand": "Nosler",
            "Caliber": "Nosler",
            "Grains": 140,
            "Price": 473.9,
            "Rounds": 200,
            "Casing": "brass",
            "S/H": "4",
            "Limits": "N/A",
            "New?": "new",
            "$/round": 2.37,
            "Link": "https://ammoseek.com/share/a/251547275773"
        },
        {
            "id": "33755863",
            "Retailer": "Black Basin",
            "Description": "NOSLER 26 NOSLER 140GR BALLISTIC TIP 20RD 10BX/CS 054041434591FREE SHIPPING on orders over $500",
            "Brand": "Nosler",
            "Caliber": "Nosler",
            "Grains": 140,
            "Price": 238.99,
            "Rounds": 100,
            "Casing": "brass",
            "S/H": "9CF",
            "Limits": "N/A",
            "New?": "new",
            "$/round": 2.39,
            "Link": "https://ammoseek.com/share/a/310974802588"
        },
        {
            "id": "14251766",
            "Retailer": "Ammo Hero",
            "Description": "NOSLER 26 NOSLER 140GR BALLISTIC TIP 20RD 10BX/CS 054041434591FREE SHIPPING on $250+",
            "Brand": "Nosler",
            "Caliber": "Nosler",
            "Grains": 140,
            "Price": 238.99,
            "Rounds": 100,
            "Casing": "brass",
            "S/H": "8CF",
            "Limits": "N/A",
            "New?": "new",
            "$/round": 2.39,
            "Link": "https://ammoseek.com/share/a/276142397518"
        },
        {
            "id": "28665731",
            "Retailer": "SST Firearms",
            "Description": "NOSLER 26 NOSLER 140GR - BALLISTIC TIP 20RD 10BX/CS 054041434591",
            "Brand": "Nosler",
            "Caliber": "Nosler",
            "Grains": 140,
            "Price": 47.84,
            "Rounds": 20,
            "Casing": "brass",
            "S/H": "8",
            "Limits": "N/A",
            "New?": "new",
            "$/round": 2.39,
            "Link": "https://ammoseek.com/share/a/281568579820"
        },
        {
            "id": "20379418",
            "Retailer": "76 Rounds",
            "Description": "Nosler Ammo BT-26 Nosler 140gr BT (20ct) 054041434591",
            "Brand": "Nosler",
            "Caliber": "Nosler",
            "Grains": 140,
            "Price": 47.99,
            "Rounds": 20,
            "Casing": "brass",
            "S/H": "7",
            "Limits": "N/A",
            "New?": "new",
            "$/round": 2.4,
            "Link": "https://ammoseek.com/share/a/297967364149"
        },
        {
            "id": "68124257",
            "Retailer": "Vizards Guns and Ammo",
            "Description": "Nosler 43459 26 Nosler Ammunition 140Gr Polymer Tipped 20 Rounds 054041434591",
            "Brand": "Nosler",
            "Caliber": "Nosler",
            "Grains": 140,
            "Price": 48.02,
            "Rounds": 20,
            "Casing": "brass",
            "S/H": "8",
            "Limits": "N/A",
            "New?": "new",
            "$/round": 2.4,
            "Link": "https://ammoseek.com/share/a/275849580946"
        },
        {
            "id": "57665887",
            "Retailer": "Georgia Guns & Ammo",
            "Description": "NOS AMMO 26NOS 140GR BT 20/10 054041434591",
            "Brand": "Nosler",
            "Caliber": "Nosler",
            "Grains": 140,
            "Price": 48.27,
            "Rounds": 20,
            "Casing": "brass",
            "S/H": "8",
            "Limits": "N/A",
            "New?": "new",
            "$/round": 2.41,
            "Link": "https://ammoseek.com/share/a/313019892136"
        },
        {
            "id": "37145727",
            "Retailer": "Chesapeake Gunslingers",
            "Description": "NOSLER BT 26 NOSLER 140GR 054041434591",
            "Brand": "Nosler",
            "Caliber": "Nosler",
            "Grains": 140,
            "Price": 48.99,
            "Rounds": 20,
            "Casing": "brass",
            "S/H": "9",
            "Limits": "N/A",
            "New?": "new",
            "$/round": 2.45,
            "Link": "https://ammoseek.com/share/a/266198945878"
        },
        {
            "id": "24431189",
            "Retailer": "DB Firearms",
            "Description": "Nosler Ballistic Tip Rifle Ammunition 26 Nosler 140 gr. BT SP 20 rd. 054041434591",
            "Brand": "Nosler",
            "Caliber": "Nosler",
            "Grains": 140,
            "Price": 48.99,
            "Rounds": 20,
            "Casing": "brass",
            "S/H": "9",
            "Limits": "N/A",
            "New?": "new",
            "$/round": 2.45,
            "Link": "https://ammoseek.com/share/a/298344805291"
        },
        {
            "id": "25263816",
            "Retailer": "American Ordnance",
            "Description": "NOSLER 26 NOSLER 140GR BALLISTIC TIP 20RD",
            "Brand": "Nosler",
            "Caliber": "Nosler",
            "Grains": 140,
            "Price": 48.99,
            "Rounds": 20,
            "Casing": "brass",
            "S/H": "8",
            "Limits": "N/A",
            "New?": "new",
            "$/round": 2.45,
            "Link": "https://ammoseek.com/share/a/313090913767"
        },
        {
            "id": "25833600",
            "Retailer": "Wholesale Hunter",
            "Description": "Nosler BT 26 Nosler 140Gr Ballistic Tip 20Rd 10Bx/Cs 054041434591",
            "Brand": "Nosler",
            "Caliber": "Nosler",
            "Grains": 140,
            "Price": 49.88,
            "Rounds": 20,
            "Casing": "brass",
            "S/H": "4",
            "Limits": "N/A",
            "New?": "new",
            "$/round": 2.49,
            "Link": "https://ammoseek.com/share/a/251547275773"
        },
        {
            "id": "28005991",
            "Retailer": "Fast Ammo",
            "Description": "Nosler Trophy Ammunition, 26, 140 Grain, AccuBond, 20 Round Box 60014 054041600149",
            "Brand": "Nosler",
            "Caliber": "Nosler",
            "Grains": 140,
            "Price": 50.8,
            "Rounds": 20,
            "Casing": "brass",
            "S/H": "3",
            "Limits": "N/A",
            "New?": "new",
            "$/round": 2.54,
            "Link": "https://ammoseek.com/share/a/274695627052"
        },
        {
            "id": "27356778",
            "Retailer": "L&M Guns and Gear",
            "Description": "Nosler Ammo BT-26 Nosler 140gr BT (20ct) 054041434591",
            "Brand": "Nosler",
            "Caliber": "Nosler",
            "Grains": 140,
            "Price": 50.99,
            "Rounds": 20,
            "Casing": "brass",
            "S/H": "2",
            "Limits": "N/A",
            "New?": "new",
            "$/round": 2.55,
            "Link": "https://ammoseek.com/share/a/310091202013"
        },
        {
            "id": "15688695",
            "Retailer": "Cabela's",
            "Description": "Nosler Ballistic Tip .26 Nosler 140 Grain Rifle Ammo 054041434591",
            "Brand": "Nosler",
            "Caliber": "Nosler",
            "Grains": 140,
            "Price": 50.99,
            "Rounds": 20,
            "Casing": "brass",
            "S/H": "8",
            "Limits": "N/A",
            "New?": "new",
            "$/round": 2.55,
            "Link": "https://ammoseek.com/share/a/259703803921"
        },
        {
            "id": "25936159",
            "Retailer": "Keen Dynamics",
            "Description": "Nosler Ballistic Tip 054041434591 26 Nosler 140 Grains Ballistic Tip",
            "Brand": "Nosler",
            "Caliber": "Nosler",
            "Grains": 140,
            "Price": 50.99,
            "Rounds": 20,
            "Casing": "brass",
            "S/H": "6",
            "Limits": "N/A",
            "New?": "new",
            "$/round": 2.55,
            "Link": "https://ammoseek.com/share/a/279196926163"
        },
        {
            "id": "57042410",
            "Retailer": "Bass Pro Shops",
            "Description": "Nosler Ballistic Tip .26 Nosler 140 Grain Rifle Ammo 054041434591",
            "Brand": "Nosler",
            "Caliber": "Nosler",
            "Grains": 140,
            "Price": 50.99,
            "Rounds": 20,
            "Casing": "brass",
            "S/H": "9",
            "Limits": "N/A",
            "New?": "new",
            "$/round": 2.55,
            "Link": "https://ammoseek.com/share/a/259703796211"
        },
        {
            "id": "24893051",
            "Retailer": "Loftus Firearms",
            "Description": "NOSLER BT 26 NOSLER 140GR 054041434591",
            "Brand": "Nosler",
            "Caliber": "Nosler",
            "Grains": 140,
            "Price": 51.0,
            "Rounds": 20,
            "Casing": "brass",
            "S/H": "9",
            "Limits": "N/A",
            "New?": "new",
            "$/round": 2.55,
            "Link": "https://ammoseek.com/share/a/284693840194"
        },
        {
            "id": "23110821",
            "Retailer": "Fast Ammo",
            "Description": "Nosler E-Tip, 26 Nosler, 120 Grain, Expansion Tip, 20 Round Box 40302 054041403023",
            "Brand": "Nosler",
            "Caliber": "Nosler",
            "Grains": 120,
            "Price": 51.68,
            "Rounds": 20,
            "Casing": "brass",
            "S/H": "3",
            "Limits": "N/A",
            "New?": "new",
            "$/round": 2.58,
            "Link": "https://ammoseek.com/share/a/274704637138"
        },
        {
            "id": "34012285",
            "Retailer": "Tactical Surplus USA",
            "Description": "Nosler Bt 26 Nosler 140gr - Ballistic Tip 20rd 10bx/cs 054041434591FREE SHIPPING on $1000+",
            "Brand": "Nosler",
            "Caliber": "Nosler",
            "Grains": 140,
            "Price": 51.91,
            "Rounds": 20,
            "Casing": "brass",
            "S/H": "8CF",
            "Limits": "N/A",
            "New?": "new",
            "$/round": 2.6,
            "Link": "https://ammoseek.com/share/a/254917113160"
        },
        {
            "id": "19846850",
            "Retailer": "Snyder Shooting Supply",
            "Description": "Nosler Ammo BT-26 Nosler 140gr BT (20ct) 054041434591",
            "Brand": "Nosler",
            "Caliber": "Nosler",
            "Grains": 140,
            "Price": 52.0,
            "Rounds": 20,
            "Casing": "brass",
            "S/H": "8",
            "Limits": "N/A",
            "New?": "new",
            "$/round": 2.6,
            "Link": "https://ammoseek.com/share/a/312669005905"
        },
        {
            "id": "12684159",
            "Retailer": "Netti Ammo",
            "Description": "NOSLER BT 26 NOSLER 140GR 054041434591",
            "Brand": "Nosler",
            "Caliber": "Nosler",
            "Grains": 140,
            "Price": 52.0,
            "Rounds": 20,
            "Casing": "brass",
            "S/H": "9",
            "Limits": "N/A",
            "New?": "new",
            "$/round": 2.6,
            "Link": "https://ammoseek.com/share/a/268208082826"
        },
        {
            "id": "29200536",
            "Retailer": "Ammo ASAP",
            "Description": "Nosler Trophy Ammunition, 26, 140 Grain, AccuBond, 20 Round Box 60014 054041600149",
            "Brand": "Nosler",
            "Caliber": "Nosler",
            "Grains": 140,
            "Price": 52.84,
            "Rounds": 20,
            "Casing": "brass",
            "S/H": "3",
            "Limits": "N/A",
            "New?": "new",
            "$/round": 2.64,
            "Link": "https://ammoseek.com/share/a/288124152781"
        },
        {
            "id": "29925046",
            "Retailer": "Rogers Sporting Goods",
            "Description": "Nosler Ammunition 26 Nosler 140 Grain Ballistic Tip Rifle Ammunition, Box of 20 | Brass 054041434591",
            "Brand": "Nosler",
            "Caliber": "Nosler",
            "Grains": 140,
            "Price": 52.99,
            "Rounds": 20,
            "Casing": "brass",
            "S/H": "9",
            "Limits": "N/A",
            "New?": "new",
            "$/round": 2.65,
            "Link": "https://ammoseek.com/share/a/265985298400"
        },
        {
            "id": "17614320",
            "Retailer": "DACK Outdoors",
            "Description": "Nosler 51288 Match Grade 26 Nosler 140 gr Custom Competition 20 Bx/ 10 Cs 054041512886Some orders take up to 30 days to ship",
            "Brand": "Nosler",
            "Caliber": "Nosler",
            "Grains": 140,
            "Price": 53.0,
            "Rounds": 20,
            "Casing": "brass",
            "S/H": "8",
            "Limits": "N/A",
            "New?": "new",
            "$/round": 2.65,
            "Link": "https://ammoseek.com/share/a/277100384905"
        },
        {
            "id": "10047092",
            "Retailer": "Gman Sporting Arms",
            "Description": "Nosler 60122 Trophy Grade Long Range 26 Nosler 142 gr AccuBond Long Range 20 Bx/ 10 Cs 054041601221",
            "Brand": "Nosler",
            "Caliber": "Nosler",
            "Grains": 142,
            "Price": 53.26,
            "Rounds": 20,
            "Casing": "brass",
            "S/H": "3",
            "Limits": "N/A",
            "New?": "new",
            "$/round": 2.66,
            "Link": "https://ammoseek.com/share/a/235126483441"
        },
        {
            "id": "11999649",
            "Retailer": "Ammo ASAP",
            "Description": "Nosler E-Tip, 26 Nosler, 120 Grain, Expansion Tip, 20 Round Box 40302 054041403023",
            "Brand": "Nosler",
            "Caliber": "Nosler",
            "Grains": 120,
            "Price": 53.72,
            "Rounds": 20,
            "Casing": "brass",
            "S/H": "3",
            "Limits": "N/A",
            "New?": "new",
            "$/round": 2.69,
            "Link": "https://ammoseek.com/share/a/288124243144"
        },
        {
            "id": "25303079",
            "Retailer": "USA Gun Store",
            "Description": "Nosler Match Grade Rifle Ammunition .26 Nosler 140gr CC 3300 fps 20/ct 054041512886",
            "Brand": "Nosler",
            "Caliber": "Nosler",
            "Grains": 140,
            "Price": 53.99,
            "Rounds": 20,
            "Casing": "brass",
            "S/H": "9",
            "Limits": "N/A",
            "New?": "new",
            "$/round": 2.7,
            "Link": "https://ammoseek.com/share/a/257891169802"
        },
        {
            "id": "31704467",
            "Retailer": "De Leon RX and Sporting Goods",
            "Description": "Nosler 51288 Match Grade 26 Nosler 140 gr Custom Competition 20 Bx/ 10 Cs 054041512886",
            "Brand": "Nosler",
            "Caliber": "Nosler",
            "Grains": 140,
            "Price": 54.64,
            "Rounds": 20,
            "Casing": "brass",
            "S/H": "8",
            "Limits": "N/A",
            "New?": "new",
            "$/round": 2.73,
            "Link": "https://ammoseek.com/share/a/276315158389"
        },
        {
            "id": "80623697",
            "Retailer": "Skogen's Gun Supply",
            "Description": "Nosler 51288 Match Grade 26 Nosler 140 gr Custom Competition 20 Bx/ 10 Cs 054041512886FREE SHIPPING on orders over $300",
            "Brand": "Nosler",
            "Caliber": "Nosler",
            "Grains": 140,
            "Price": 54.95,
            "Rounds": 20,
            "Casing": "brass",
            "S/H": "6CF",
            "Limits": "N/A",
            "New?": "new",
            "$/round": 2.75,
            "Link": "https://ammoseek.com/share/a/276318276040"
        },
        {
            "id": "28847174",
            "Retailer": "GrabAGun",
            "Description": "Nosler Match Grade .26 Nosler Ammunition 20 Rounds 140 Grain BTHP 3300fps - $12.99 Shipping on Unlimited Boxes - UPC: 054041512886",
            "Brand": "Nosler",
            "Caliber": "Nosler",
            "Grains": 140,
            "Price": 54.99,
            "Rounds": 20,
            "Casing": "brass",
            "S/H": "8",
            "Limits": "N/A",
            "New?": "new",
            "$/round": 2.75,
            "Link": "https://ammoseek.com/share/a/71776282213"
        },
        {
            "id": "60059799",
            "Retailer": "Fast Ammo",
            "Description": "Nosler 51288 Match Grade 26Nosler 140gr Custom Competition Hollow Point Boat Tail 20 Per Box/10 Case 054041512886",
            "Brand": "Nosler",
            "Caliber": "Nosler",
            "Grains": 140,
            "Price": 55.04,
            "Rounds": 20,
            "Casing": "brass",
            "S/H": "3",
            "Limits": "N/A",
            "New?": "new",
            "$/round": 2.75,
            "Link": "https://ammoseek.com/share/a/274704636088"
        },
        {
            "id": "49386542",
            "Retailer": "Armed In Michigan",
            "Description": "Nosler Match Grade Rifle Ammunition .26 Nosler 140gr CC 3300 fps 20/ct 054041512886",
            "Brand": "Nosler",
            "Caliber": "Nosler",
            "Grains": 140,
            "Price": 55.99,
            "Rounds": 20,
            "Casing": "brass",
            "S/H": "8",
            "Limits": "N/A",
            "New?": "new",
            "$/round": 2.8,
            "Link": "https://ammoseek.com/share/a/295256808520"
        },
        {
            "id": "33343031",
            "Retailer": "Palmetto State Armory",
            "Description": "Nosler Ballistic Tip .26 Nosler 140 gr BTPT 20rds 54041434591",
            "Brand": "Nosler",
            "Caliber": "Nosler",
            "Grains": 140,
            "Price": 55.99,
            "Rounds": 20,
            "Casing": "brass",
            "S/H": "5",
            "Limits": "N/A",
            "New?": "new",
            "$/round": 2.8,
            "Link": "https://ammoseek.com/share/a/307942026898"
        },
        {
            "id": "27642601",
            "Retailer": "Gman Sporting Arms",
            "Description": "Nosler 60014 Trophy Grade 26 Nosler 140 gr AccuBond 20 Bx/ 10 Cs 054041600149",
            "Brand": "Nosler",
            "Caliber": "Nosler",
            "Grains": 140,
            "Price": 56.12,
            "Rounds": 20,
            "Casing": "brass",
            "S/H": "3",
            "Limits": "N/A",
            "New?": "new",
            "$/round": 2.81,
            "Link": "https://ammoseek.com/share/a/243598939624"
        },
        {
            "id": "28748783",
            "Retailer": "Black Basin",
            "Description": "NOSLER 26 NOSLER 140GR BALLISTIC TIP 20RD 10BX/CS 054041434591FREE SHIPPING on orders over $500",
            "Brand": "Nosler",
            "Caliber": "Nosler",
            "Grains": 140,
            "Price": 56.18,
            "Rounds": 20,
            "Casing": "brass",
            "S/H": "9CF",
            "Limits": "N/A",
            "New?": "new",
            "$/round": 2.81,
            "Link": "https://ammoseek.com/share/a/310974802585"
        },
        {
            "id": "25630299",
            "Retailer": "Firearms Depot",
            "Description": "Nosler Match Grade .26 NOS, 140gr, CC - 20 Rounds [MPN: 51288] 054041512886",
            "Brand": "Nosler",
            "Caliber": "Nosler",
            "Grains": 140,
            "Price": 56.5,
            "Rounds": 20,
            "Casing": "brass",
            "S/H": "5",
            "Limits": "N/A",
            "New?": "new",
            "$/round": 2.83,
            "Link": "https://ammoseek.com/share/a/241344272221"
        },
        {
            "id": "33282135",
            "Retailer": "Fast Ammo",
            "Description": "Nosler Trophy Long Range, 26 142 Grain, AccuBond, 20 Round Box 60122 054041601221",
            "Brand": "Nosler",
            "Caliber": "Nosler",
            "Grains": 142,
            "Price": 56.62,
            "Rounds": 20,
            "Casing": "brass",
            "S/H": "3",
            "Limits": "N/A",
            "New?": "new",
            "$/round": 2.83,
            "Link": "https://ammoseek.com/share/a/274694404930"
        },
        {
            "id": "16266752",
            "Retailer": "Ammo ASAP",
            "Description": "Nosler Trophy Long Range, 26 142 Grain, AccuBond, 20 Round Box 60122 054041601221",
            "Brand": "Nosler",
            "Caliber": "Nosler",
            "Grains": 142,
            "Price": 56.62,
            "Rounds": 20,
            "Casing": "brass",
            "S/H": "3",
            "Limits": "N/A",
            "New?": "new",
            "$/round": 2.83,
            "Link": "https://ammoseek.com/share/a/288124134625"
        },
        {
            "id": "19542779",
            "Retailer": "Fast Ammo",
            "Description": "Nosler Trophy Long Range, 26 142 Grain, AccuBond, 20 Round Box 60122 054041601221",
            "Brand": "Nosler",
            "Caliber": "Nosler",
            "Grains": 142,
            "Price": 113.24,
            "Rounds": 40,
            "Casing": "brass",
            "S/H": "3",
            "Limits": "N/A",
            "New?": "new",
            "$/round": 2.83,
            "Link": "https://ammoseek.com/share/a/274694404939"
        },
        {
            "id": "31717665",
            "Retailer": "Ammo ASAP",
            "Description": "Nosler Trophy Long Range, 26 142 Grain, AccuBond, 20 Round Box 60122 054041601221",
            "Brand": "Nosler",
            "Caliber": "Nosler",
            "Grains": 142,
            "Price": 113.24,
            "Rounds": 40,
            "Casing": "brass",
            "S/H": "3",
            "Limits": "N/A",
            "New?": "new",
            "$/round": 2.83,
            "Link": "https://ammoseek.com/share/a/288124134610"
        },
        {
            "id": "72146402",
            "Retailer": "Fast Ammo",
            "Description": "Nosler Trophy Long Range, 26 142 Grain, AccuBond, 20 Round Box 60122 054041601221",
            "Brand": "Nosler",
            "Caliber": "Nosler",
            "Grains": 142,
            "Price": 226.48,
            "Rounds": 80,
            "Casing": "brass",
            "S/H": "3",
            "Limits": "N/A",
            "New?": "new",
            "$/round": 2.83,
            "Link": "https://ammoseek.com/share/a/274694404945"
        },
        {
            "id": "20924935",
            "Retailer": "Ammo ASAP",
            "Description": "Nosler Trophy Long Range, 26 142 Grain, AccuBond, 20 Round Box 60122 054041601221",
            "Brand": "Nosler",
            "Caliber": "Nosler",
            "Grains": 142,
            "Price": 226.48,
            "Rounds": 80,
            "Casing": "brass",
            "S/H": "3",
            "Limits": "N/A",
            "New?": "new",
            "$/round": 2.83,
            "Link": "https://ammoseek.com/share/a/288124134589"
        },
        {
            "id": "23483576",
            "Retailer": "Fast Ammo",
            "Description": "Nosler 60110 Trophy Grade Long-Range 26Nosler 129gr Nosler Spitzer AccuBond Long Range 20 Per Box/10 Case 054041601108",
            "Brand": "Nosler",
            "Caliber": "Nosler",
            "Grains": 129,
            "Price": 56.68,
            "Rounds": 20,
            "Casing": "brass",
            "S/H": "3",
            "Limits": "N/A",
            "New?": "new",
            "$/round": 2.83,
            "Link": "https://ammoseek.com/share/a/274704636124"
        },
        {
            "id": "13467129",
            "Retailer": "Ammo ASAP",
            "Description": "Nosler 60110 Trophy Grade Long-Range 26Nosler 129gr Nosler Spitzer AccuBond Long Range 20 Per Box/10 Case 054041601108",
            "Brand": "Nosler",
            "Caliber": "Nosler",
            "Grains": 129,
            "Price": 56.72,
            "Rounds": 20,
            "Casing": "brass",
            "S/H": "3",
            "Limits": "N/A",
            "New?": "new",
            "$/round": 2.84,
            "Link": "https://ammoseek.com/share/a/288124229182"
        },
        {
            "id": "14036079",
            "Retailer": "Fast Ammo",
            "Description": "Nosler 60110 Trophy Grade Long-Range 26Nosler 129gr Nosler Spitzer AccuBond Long Range 20 Per Box/10 Case 054041601108",
            "Brand": "Nosler",
            "Caliber": "Nosler",
            "Grains": 129,
            "Price": 113.84,
            "Rounds": 40,
            "Casing": "brass",
            "S/H": "3",
            "Limits": "N/A",
            "New?": "new",
            "$/round": 2.85,
            "Link": "https://ammoseek.com/share/a/274704636127"
        },
        {
            "id": "28613293",
            "Retailer": "Ammo ASAP",
            "Description": "Nosler 60110 Trophy Grade Long-Range 26Nosler 129gr Nosler Spitzer AccuBond Long Range 20 Per Box/10 Case 054041601108",
            "Brand": "Nosler",
            "Caliber": "Nosler",
            "Grains": 129,
            "Price": 113.84,
            "Rounds": 40,
            "Casing": "brass",
            "S/H": "3",
            "Limits": "N/A",
            "New?": "new",
            "$/round": 2.85,
            "Link": "https://ammoseek.com/share/a/288124229167"
        },
        {
            "id": "18914669",
            "Retailer": "Hinterland Outfitters",
            "Description": "Nosler 51288 Match Grade 26 Nosler 140 gr Custom Competition Hollow Point Boat Tail 20 Per Box/ 10 Cs 054041512886",
            "Brand": "Nosler",
            "Caliber": "Nosler",
            "Grains": 140,
            "Price": 56.94,
            "Rounds": 20,
            "Casing": "brass",
            "S/H": "8",
            "Limits": "N/A",
            "New?": "new",
            "$/round": 2.85,
            "Link": "https://ammoseek.com/share/a/282444591595"
        },
        {
            "id": "25185586",
            "Retailer": "Big Mike's Guns and Ammo",
            "Description": "Nosler 51288 Match Grade 26 Nosler 140 gr Custom Competition Hollow Point Boat Tail 20 Per Box/ 10 Cs 054041512886",
            "Brand": "Nosler",
            "Caliber": "Nosler",
            "Grains": 140,
            "Price": 57.0,
            "Rounds": 20,
            "Casing": "brass",
            "S/H": "9",
            "Limits": "N/A",
            "New?": "new",
            "$/round": 2.85,
            "Link": "https://ammoseek.com/share/a/285208218865"
        },
        {
            "id": "18525506",
            "Retailer": "Ammo ASAP",
            "Description": "Nosler 51288 Match Grade 26Nosler 140gr Custom Competition Hollow Point Boat Tail 20 Per Box/10 Case 054041512886",
            "Brand": "Nosler",
            "Caliber": "Nosler",
            "Grains": 140,
            "Price": 57.09,
            "Rounds": 20,
            "Casing": "brass",
            "S/H": "3",
            "Limits": "N/A",
            "New?": "new",
            "$/round": 2.85,
            "Link": "https://ammoseek.com/share/a/288124229017"
        },
        {
            "id": "24811870",
            "Retailer": "Gman Sporting Arms",
            "Description": "Nosler 60110 Trophy Grade Long Range 26 Nosler 129 gr AccuBond Long Range 20 Bx/ 10 Cs 054041601108",
            "Brand": "Nosler",
            "Caliber": "Nosler",
            "Grains": 129,
            "Price": 57.27,
            "Rounds": 20,
            "Casing": "brass",
            "S/H": "3",
            "Limits": "N/A",
            "New?": "new",
            "$/round": 2.86,
            "Link": "https://ammoseek.com/share/a/235378024378"
        },
        {
            "id": "12818259",
            "Retailer": "MidwayUSA",
            "Description": "Nosler Trophy Grade 26 Nosler Ammo 142 Grain Nosler AccuBond Long Range Bonded Polymer Tip Box of 20 054041601221",
            "Brand": "Nosler",
            "Caliber": "Nosler",
            "Grains": 142,
            "Price": 57.62,
            "Rounds": 20,
            "Casing": "brass",
            "S/H": "8",
            "Limits": "N/A",
            "New?": "new",
            "$/round": 2.88,
            "Link": "https://ammoseek.com/share/a/269107115461"
        },
        {
            "id": "14743856",
            "Retailer": "Ammo ASAP",
            "Description": "Nosler Trophy Ammunition, 26, 140 Grain, AccuBond, 20 Round Box 60014 054041600149",
            "Brand": "Nosler",
            "Caliber": "Nosler",
            "Grains": 140,
            "Price": 115.81,
            "Rounds": 40,
            "Casing": "brass",
            "S/H": "3",
            "Limits": "N/A",
            "New?": "new",
            "$/round": 2.9,
            "Link": "https://ammoseek.com/share/a/288124152757"
        },
        {
            "id": "22181344",
            "Retailer": "Fast Ammo",
            "Description": "Nosler Trophy Ammunition, 26, 140 Grain, AccuBond, 20 Round Box 60014 054041600149",
            "Brand": "Nosler",
            "Caliber": "Nosler",
            "Grains": 140,
            "Price": 115.81,
            "Rounds": 40,
            "Casing": "brass",
            "S/H": "3",
            "Limits": "N/A",
            "New?": "new",
            "$/round": 2.9,
            "Link": "https://ammoseek.com/share/a/274695627064"
        },
        {
            "id": "19500848",
            "Retailer": "Shooting Surplus",
            "Description": "Nosler Match Grade Rifle Ammunition 26 Nosler 140 gr. CC HPBT 20 rd. 054041512886",
            "Brand": "Nosler",
            "Caliber": "Nosler",
            "Grains": 140,
            "Price": 58.82,
            "Rounds": 20,
            "Casing": "brass",
            "S/H": "8",
            "Limits": "N/A",
            "New?": "new",
            "$/round": 2.94,
            "Link": "https://ammoseek.com/share/a/293798982310"
        },
        {
            "id": "23321831",
            "Retailer": "Republic Ammunition",
            "Description": "Nosler .26 Nosler 142gr Ablr 20CT - 20 RPLNOS60122",
            "Brand": "Nosler",
            "Caliber": "Nosler",
            "Grains": 142,
            "Price": 59.34,
            "Rounds": 20,
            "Casing": "brass",
            "S/H": "7",
            "Limits": "N/A",
            "New?": "new",
            "$/round": 2.97,
            "Link": "https://ammoseek.com/share/a/276633059848"
        },
        {
            "id": "19806229",
            "Retailer": "Ammo City Supply",
            "Description": "Nosler 26nos 142gr Ablr 20/200 054041601221",
            "Brand": "Nosler",
            "Caliber": "Nosler",
            "Grains": 142,
            "Price": 59.63,
            "Rounds": 20,
            "Casing": "brass",
            "S/H": "7",
            "Limits": "N/A",
            "New?": "new",
            "$/round": 2.98,
            "Link": "https://ammoseek.com/share/a/237517995801"
        },
        {
            "id": "16036436",
            "Retailer": "Ammunition1.Direct",
            "Description": "Nosler 60122 Trophy Grade Long Range 26 Nosler 142 gr AccuBond Long Range 20 Bx/ 10 Cs 054041601221",
            "Brand": "Nosler",
            "Caliber": "Nosler",
            "Grains": 142,
            "Price": 60.3,
            "Rounds": 20,
            "Casing": "brass",
            "S/H": "9",
            "Limits": "N/A",
            "New?": "new",
            "$/round": 3.02,
            "Link": "https://ammoseek.com/share/a/294321019942"
        },
        {
            "id": "17197068",
            "Retailer": "Ammo ASAP",
            "Description": "Nosler Trophy Ammunition, 26, 140 Grain, AccuBond, 20 Round Box 60014 054041600149",
            "Brand": "Nosler",
            "Caliber": "Nosler",
            "Grains": 140,
            "Price": 242.46,
            "Rounds": 80,
            "Casing": "brass",
            "S/H": "3",
            "Limits": "N/A",
            "New?": "new",
            "$/round": 3.03,
            "Link": "https://ammoseek.com/share/a/288124152739"
        },
        {
            "id": "23298959",
            "Retailer": "Fast Ammo",
            "Description": "Nosler Trophy Ammunition, 26, 140 Grain, AccuBond, 20 Round Box 60014 054041600149",
            "Brand": "Nosler",
            "Caliber": "Nosler",
            "Grains": 140,
            "Price": 242.46,
            "Rounds": 80,
            "Casing": "brass",
            "S/H": "3",
            "Limits": "N/A",
            "New?": "new",
            "$/round": 3.03,
            "Link": "https://ammoseek.com/share/a/274695627085"
        },
        {
            "id": "18244045",
            "Retailer": "Minutemen Defense",
            "Description": "NOSLER 26NOS 142GR ABLR 20/200 054041601221",
            "Brand": "Nosler",
            "Caliber": "Nosler",
            "Grains": 142,
            "Price": 60.78,
            "Rounds": 20,
            "Casing": "brass",
            "S/H": "9",
            "Limits": "N/A",
            "New?": "new",
            "$/round": 3.04,
            "Link": "https://ammoseek.com/share/a/270387980605"
        },
        {
            "id": "12943474",
            "Retailer": "All Alpha Armory",
            "Description": "Nosler 60122 Trophy Grade Long Range 26 Nosler 142 gr AccuBond Long Range 20 Bx/ 10 Cs 054041601221",
            "Brand": "Nosler",
            "Caliber": "Nosler",
            "Grains": 142,
            "Price": 60.78,
            "Rounds": 20,
            "Casing": "brass",
            "S/H": "7",
            "Limits": "N/A",
            "New?": "new",
            "$/round": 3.04,
            "Link": "https://ammoseek.com/share/a/281428449067"
        },
        {
            "id": "93562807",
            "Retailer": "BattleHawk Armory",
            "Description": "Nosler 60122 Trophy Grade Long Range 26 Nosler 142 gr AccuBond Long Range 20 Bx/ 10 Cs 054041601221",
            "Brand": "Nosler",
            "Caliber": "Nosler",
            "Grains": 142,
            "Price": 60.94,
            "Rounds": 20,
            "Casing": "brass",
            "S/H": "3",
            "Limits": "N/A",
            "New?": "new",
            "$/round": 3.05,
            "Link": "https://ammoseek.com/share/a/234354777679"
        },
        {
            "id": "10685664",
            "Retailer": "Red River Reloading",
            "Description": "Nosler Trophy Grade LR 26 Nosler 142gr AccuBond LR /20",
            "Brand": "Nosler",
            "Caliber": "Nosler",
            "Grains": 142,
            "Price": 61.36,
            "Rounds": 20,
            "Casing": "brass",
            "S/H": "6",
            "Limits": "N/A",
            "New?": "new",
            "$/round": 3.07,
            "Link": "https://ammoseek.com/share/a/177554309380"
        },
        {
            "id": "16380409",
            "Retailer": "DACK Outdoors",
            "Description": "Nosler 60122 Trophy Grade Long Range 26 Nosler 142 gr AccuBond Long Range 20 Bx/ 10 Cs 054041601221Some orders take up to 30 days to ship",
            "Brand": "Nosler",
            "Caliber": "Nosler",
            "Grains": 142,
            "Price": 61.36,
            "Rounds": 20,
            "Casing": "brass",
            "S/H": "8",
            "Limits": "N/A",
            "New?": "new",
            "$/round": 3.07,
            "Link": "https://ammoseek.com/share/a/277100387992"
        },
        {
            "id": "20795678",
            "Retailer": "Gman Sporting Arms",
            "Description": "Nosler 40302 E-Tip 26 Nosler 120 gr E-Tip Lead-Free 20 Bx/ 10 Cs 054041403023",
            "Brand": "Nosler",
            "Caliber": "Nosler",
            "Grains": 120,
            "Price": 61.4,
            "Rounds": 20,
            "Casing": "brass",
            "S/H": "3",
            "Limits": "N/A",
            "New?": "new",
            "$/round": 3.07,
            "Link": "https://ammoseek.com/share/a/243598939576"
        },
        {
            "id": "22717543",
            "Retailer": "Fast Ammo",
            "Description": "Nosler 60110 Trophy Grade Long-Range 26Nosler 129gr Nosler Spitzer AccuBond Long Range 20 Per Box/10 Case 054041601108",
            "Brand": "Nosler",
            "Caliber": "Nosler",
            "Grains": 129,
            "Price": 246.96,
            "Rounds": 80,
            "Casing": "brass",
            "S/H": "3",
            "Limits": "N/A",
            "New?": "new",
            "$/round": 3.09,
            "Link": "https://ammoseek.com/share/a/274704636130"
        },
        {
            "id": "14596069",
            "Retailer": "Ammo ASAP",
            "Description": "Nosler 60110 Trophy Grade Long-Range 26Nosler 129gr Nosler Spitzer AccuBond Long Range 20 Per Box/10 Case 054041601108",
            "Brand": "Nosler",
            "Caliber": "Nosler",
            "Grains": 129,
            "Price": 246.96,
            "Rounds": 80,
            "Casing": "brass",
            "S/H": "3",
            "Limits": "N/A",
            "New?": "new",
            "$/round": 3.09,
            "Link": "https://ammoseek.com/share/a/288124229146"
        },
        {
            "id": "22034469",
            "Retailer": "Tactical Surplus USA",
            "Description": "Nosler 26nos 142gr Ablr 20/200 54041601221FREE SHIPPING on $1000+",
            "Brand": "Nosler",
            "Caliber": "Nosler",
            "Grains": 142,
            "Price": 61.94,
            "Rounds": 20,
            "Casing": "brass",
            "S/H": "8CF",
            "Limits": "N/A",
            "New?": "new",
            "$/round": 3.1,
            "Link": "https://ammoseek.com/share/a/235141027846"
        },
        {
            "id": "22683621",
            "Retailer": "USA Gun Store",
            "Description": "Nosler 60122 Trophy Grade Long-Range 26 Nosler 142 gr Nosler Spitzer AccuBond Long Range 20 Per Box/ 10 Cs 054041601221",
            "Brand": "Nosler",
            "Caliber": "Nosler",
            "Grains": 142,
            "Price": 61.99,
            "Rounds": 20,
            "Casing": "brass",
            "S/H": "9",
            "Limits": "N/A",
            "New?": "new",
            "$/round": 3.1,
            "Link": "https://ammoseek.com/share/a/257891175913"
        },
        {
            "id": "13746916",
            "Retailer": "Prepper Gun Shop",
            "Description": "NOSLER Trophy Long Range 26 Nosler 142Gr AccuBond 20rd 054041601221",
            "Brand": "Nosler",
            "Caliber": "Nosler",
            "Grains": 142,
            "Price": 61.99,
            "Rounds": 20,
            "Casing": "brass",
            "S/H": "9",
            "Limits": "N/A",
            "New?": "new",
            "$/round": 3.1,
            "Link": "https://ammoseek.com/share/a/299173956886"
        },
        {
            "id": "57233275",
            "Retailer": "Fast Ammo",
            "Description": "Nosler 51288 Match Grade 26Nosler 140gr Custom Competition Hollow Point Boat Tail 20 Per Box/10 Case 054041512886",
            "Brand": "Nosler",
            "Caliber": "Nosler",
            "Grains": 140,
            "Price": 124.25,
            "Rounds": 40,
            "Casing": "brass",
            "S/H": "3",
            "Limits": "N/A",
            "New?": "new",
            "$/round": 3.11,
            "Link": "https://ammoseek.com/share/a/274704636091"
        }
    ]
}