{
    "results": [
        {
            "Retailer": "Gman Sporting Arms",
            "Description": "Hornady 82733 LEVERevolution 308 Marlin Express 160 gr Flex Tip eXpanding 20 Bx/ 10 Cs 090255827330",
            "Brand": "Hornady",
            "Caliber": "Marlin Express",
            "Grains": 160,
            "Price": 26.54,
            "Rounds": 20,
            "Casing": "brass",
            "S/H": "3",
            "Limits": "N/A",
            "New?": "new",
            "$/round": 1.33,
            "Link": "https://ammoseek.com/share/a/245096184670"
        },
        {
            "Retailer": "SGAmmo",
            "Description": "200 Round Case - 308 Marlin Express 160 Grain FTX Hornady LeverEvolution Ammo - 82733- Free Shipping",
            "Brand": "Hornady",
            "Caliber": "Marlin Express",
            "Grains": 160,
            "Price": 299.5,
            "Rounds": 200,
            "Casing": "brass",
            "S/H": "F",
            "Limits": "N/A",
            "New?": "new",
            "$/round": 1.5,
            "Link": "https://ammoseek.com/share/a/168032354717"
        },
        {
            "Retailer": "Foundry Outdoors",
            "Description": "Hornady 82733 LEVERevolution 308 Marlin Express 160 GR 20 Bx/10 Cs 090255827330",
            "Brand": "Hornady",
            "Caliber": "Marlin Express",
            "Grains": 160,
            "Price": 30.39,
            "Rounds": 20,
            "Casing": "brass",
            "S/H": "4",
            "Limits": "N/A",
            "New?": "new",
            "$/round": 1.52,
            "Link": "https://ammoseek.com/share/a/280781658916"
        },
        {
            "Retailer": "Ammo City Supply",
            "Description": "Hrndy Lvrevo 308mrln Exps 160gr 20rd 090255827330",
            "Brand": "Hornady",
            "Caliber": "Marlin Express",
            "Grains": 160,
            "Price": 30.89,
            "Rounds": 20,
            "Casing": "brass",
            "S/H": "7",
            "Limits": "N/A",
            "New?": "new",
            "$/round": 1.54,
            "Link": "https://ammoseek.com/share/a/307939297930"
        },
        {
            "Retailer": "DACK Outdoors",
            "Description": "Hornady 82733 LEVERevolution 308 Marlin Express 160 gr Flex Tip eXpanding 20 Bx/ 10 Cs 090255827330Some orders take up to 30 days to ship",
            "Brand": "Hornady",
            "Caliber": "Marlin Express",
            "Grains": 160,
            "Price": 30.95,
            "Rounds": 20,
            "Casing": "brass",
            "S/H": "8",
            "Limits": "N/A",
            "New?": "new",
            "$/round": 1.55,
            "Link": "https://ammoseek.com/share/a/280775078290"
        },
        {
            "Retailer": "LG Outdoors",
            "Description": "Hornady LEVERevolution Rifle Ammo 308 Marlin Express 160 gr Flex Tip eXpanding 20 rd Model: 82733(Price per unit for order of 10+ units)090255827330",
            "Brand": "Hornady",
            "Caliber": "Marlin Express",
            "Grains": 160,
            "Price": 31.22,
            "Rounds": 20,
            "Casing": "brass",
            "S/H": "5",
            "Limits": "N/A",
            "New?": "new",
            "$/round": 1.56,
            "Link": "https://ammoseek.com/share/a/314021120275"
        },
        {
            "Retailer": "Ammo Sale",
            "Description": "Hornady LEVERevolution Rifle Ammo 308 Marlin Express 160 gr Flex Tip eXpanding 20 rd Model: 82733(Price per unit for order of 10+ units)090255827330",
            "Brand": "Hornady",
            "Caliber": "Marlin Express",
            "Grains": 160,
            "Price": 31.22,
            "Rounds": 20,
            "Casing": "brass",
            "S/H": "5",
            "Limits": "N/A",
            "New?": "new",
            "$/round": 1.56,
            "Link": "https://ammoseek.com/share/a/314022624136"
        },
        {
            "Retailer": "Wholesale Hunter",
            "Description": "308 Marlin 20 Rounds Ammunition Hornady 160 Grain FTX Case of 200 090255827330(price reflects 5% bulk discount)",
            "Brand": "Hornady",
            "Caliber": "Marlin Express",
            "Grains": 160,
            "Price": 312.2,
            "Rounds": 200,
            "Casing": "brass",
            "S/H": "4",
            "Limits": "N/A",
            "New?": "new",
            "$/round": 1.56,
            "Link": "https://ammoseek.com/share/a/45819492246"
        },
        {
            "Retailer": "Ammunition1.Direct",
            "Description": "Hornady 82733 LEVERevolution 308 Marlin Express 160 gr Flex Tip eXpanding 20 Bx/ 10 Cs 090255827330",
            "Brand": "Hornady",
            "Caliber": "Marlin Express",
            "Grains": 160,
            "Price": 31.24,
            "Rounds": 20,
            "Casing": "brass",
            "S/H": "9",
            "Limits": "N/A",
            "New?": "new",
            "$/round": 1.56,
            "Link": "https://ammoseek.com/share/a/294321016897"
        },
        {
            "Retailer": "Minutemen Defense",
            "Description": "HRNDY LVREVO 308MRLN EXPS 160GR 20RD 090255827330",
            "Brand": "Hornady",
            "Caliber": "Marlin Express",
            "Grains": 160,
            "Price": 31.49,
            "Rounds": 20,
            "Casing": "brass",
            "S/H": "9",
            "Limits": "N/A",
            "New?": "new",
            "$/round": 1.57,
            "Link": "https://ammoseek.com/share/a/280741644073"
        },
        {
            "Retailer": "All Alpha Armory",
            "Description": "Hornady 82733 LEVERevolution 308 Marlin Express 160 gr Flex Tip eXpanding 20 Bx/ 10 Cs 090255827330",
            "Brand": "Hornady",
            "Caliber": "Marlin Express",
            "Grains": 160,
            "Price": 31.49,
            "Rounds": 20,
            "Casing": "brass",
            "S/H": "7",
            "Limits": "N/A",
            "New?": "new",
            "$/round": 1.57,
            "Link": "https://ammoseek.com/share/a/282030600403"
        },
        {
            "Retailer": "Red River Reloading",
            "Description": "Hornady LeverEvolution 308 Marlin Express 160gr FTX /20 (Buy 2 $31.79 Each)",
            "Brand": "Hornady",
            "Caliber": "Marlin Express",
            "Grains": 160,
            "Price": 63.58,
            "Rounds": 40,
            "Casing": "brass",
            "S/H": "6",
            "Limits": "N/A",
            "New?": "new",
            "$/round": 1.59,
            "Link": "https://ammoseek.com/share/a/280762159201"
        },
        {
            "Retailer": "Kevin's Ammo Yard",
            "Description": "Hornady 82733 Leverevolution 308 Marlin Express, 160GR, FTX, 20RD Per Box, 090255827330 090255827330",
            "Brand": "Hornady",
            "Caliber": "Marlin Express",
            "Grains": 160,
            "Price": 31.85,
            "Rounds": 20,
            "Casing": "brass",
            "S/H": "6",
            "Limits": "N/A",
            "New?": "new",
            "$/round": 1.59,
            "Link": "https://ammoseek.com/share/a/282731742925"
        },
        {
            "Retailer": "De Leon RX and Sporting Goods",
            "Description": "Hornady 82733 LEVERevolution 308 Marlin Express 160 gr Flex Tip eXpanding 20 Bx/ 10 Cs 090255827330",
            "Brand": "Hornady",
            "Caliber": "Marlin Express",
            "Grains": 160,
            "Price": 31.91,
            "Rounds": 20,
            "Casing": "brass",
            "S/H": "8",
            "Limits": "N/A",
            "New?": "new",
            "$/round": 1.59,
            "Link": "https://ammoseek.com/share/a/279675929557"
        },
        {
            "Retailer": "Prepper Gun Shop",
            "Description": "Hornady LeverEvolution 308 Marlin Express 160Gr FlexTip 20rd 090255827330",
            "Brand": "Hornady",
            "Caliber": "Marlin Express",
            "Grains": 160,
            "Price": 31.99,
            "Rounds": 20,
            "Casing": "brass",
            "S/H": "9",
            "Limits": "N/A",
            "New?": "new",
            "$/round": 1.6,
            "Link": "https://ammoseek.com/share/a/299174985538"
        },
        {
            "Retailer": "Sportsman Fulfillment",
            "Description": "Hornady 82733 LEVERevolution 308 Marlin Express 160 GR FTX 20 Rounds 090255827330",
            "Brand": "Hornady",
            "Caliber": "Marlin Express",
            "Grains": 160,
            "Price": 31.99,
            "Rounds": 20,
            "Casing": "brass",
            "S/H": "6",
            "Limits": "N/A",
            "New?": "new",
            "$/round": 1.6,
            "Link": "https://ammoseek.com/share/a/245062821604"
        },
        {
            "Retailer": "Foundry Outdoors",
            "Description": "Hornady Ammo Leverevolution .308 Marlin 160gr. FTX 20-Pack 090255827330",
            "Brand": "Hornady",
            "Caliber": "Marlin Express",
            "Grains": 160,
            "Price": 32.01,
            "Rounds": 20,
            "Casing": "brass",
            "S/H": "4",
            "Limits": "N/A",
            "New?": "new",
            "$/round": 1.6,
            "Link": "https://ammoseek.com/share/a/284045982019"
        },
        {
            "Retailer": "Tactical Surplus USA",
            "Description": "Hrndy Lvrevo 308mrln Exps 160gr 20rd 90255827330FREE SHIPPING on $1000+",
            "Brand": "Hornady",
            "Caliber": "Marlin Express",
            "Grains": 160,
            "Price": 32.09,
            "Rounds": 20,
            "Casing": "brass",
            "S/H": "8CF",
            "Limits": "N/A",
            "New?": "new",
            "$/round": 1.6,
            "Link": "https://ammoseek.com/share/a/248514418291"
        },
        {
            "Retailer": "Skogen's Gun Supply",
            "Description": "Hornady 82733 LEVERevolution 308 Marlin Express 160 gr Flex Tip eXpanding 20 Bx/ 10 Cs 090255827330FREE SHIPPING on orders over $300",
            "Brand": "Hornady",
            "Caliber": "Marlin Express",
            "Grains": 160,
            "Price": 32.09,
            "Rounds": 20,
            "Casing": "brass",
            "S/H": "6CF",
            "Limits": "N/A",
            "New?": "new",
            "$/round": 1.6,
            "Link": "https://ammoseek.com/share/a/248507221750"
        },
        {
            "Retailer": "GrabAGun",
            "Description": "Hornady LeverEvolution .308 MAR 160GR FT 20Rds - $12.99 Shipping on Unlimited Boxes - UPC: 090255827330",
            "Brand": "Hornady",
            "Caliber": "Marlin Express",
            "Grains": 160,
            "Price": 32.19,
            "Rounds": 20,
            "Casing": "brass",
            "S/H": "8",
            "Limits": "N/A",
            "New?": "new",
            "$/round": 1.61,
            "Link": "https://ammoseek.com/share/a/71776277209"
        },
        {
            "Retailer": "Vizards Guns and Ammo",
            "Description": "HRNDY LVREVO 308MRLN EXPS 160GR 20RD 090255827330",
            "Brand": "Hornady",
            "Caliber": "Marlin Express",
            "Grains": 160,
            "Price": 32.39,
            "Rounds": 20,
            "Casing": "brass",
            "S/H": "8",
            "Limits": "N/A",
            "New?": "new",
            "$/round": 1.62,
            "Link": "https://ammoseek.com/share/a/269774361706"
        },
        {
            "Retailer": "Apex Ordnance",
            "Description": "HORNADY LEVEREVOLUTION 168GR 308 MARLIN FTX 20RD 10BX/CS 090255827330",
            "Brand": "Hornady",
            "Caliber": "Marlin Express",
            "Grains": 168,
            "Price": 32.55,
            "Rounds": 20,
            "Casing": "brass",
            "S/H": "9",
            "Limits": "N/A",
            "New?": "new",
            "$/round": 1.63,
            "Link": "https://ammoseek.com/share/a/298585943545"
        },
        {
            "Retailer": "MCM Tactical",
            "Description": "Hornady LEVERevolution Rifle Ammunition .308 Marlin 160 gr FTX 2660 fps - 20/box 090255827330",
            "Brand": "Hornady",
            "Caliber": "Marlin Express",
            "Grains": 160,
            "Price": 32.63,
            "Rounds": 20,
            "Casing": "brass",
            "S/H": "8",
            "Limits": "N/A",
            "New?": "new",
            "$/round": 1.63,
            "Link": "https://ammoseek.com/share/a/279674675779"
        },
        {
            "Retailer": "LG Outdoors",
            "Description": "308 Marlin 160 Grain Flex Tip Expanding 20 Rounds Hornady Ammunition(Price per unit for order of 10+ units)090255827330",
            "Brand": "Hornady",
            "Caliber": "Marlin Express",
            "Grains": 160,
            "Price": 32.74,
            "Rounds": 20,
            "Casing": "brass",
            "S/H": "5",
            "Limits": "N/A",
            "New?": "new",
            "$/round": 1.64,
            "Link": "https://ammoseek.com/share/a/124268748815"
        },
        {
            "Retailer": "Ammo Sale",
            "Description": "308 Marlin 160 Grain Flex Tip Expanding 20 Rounds Hornady Ammunition(Price per unit for order of 10+ units)090255827330",
            "Brand": "Hornady",
            "Caliber": "Marlin Express",
            "Grains": 160,
            "Price": 32.74,
            "Rounds": 20,
            "Casing": "brass",
            "S/H": "5",
            "Limits": "N/A",
            "New?": "new",
            "$/round": 1.64,
            "Link": "https://ammoseek.com/share/a/247945080229"
        },
        {
            "Retailer": "Wholesale Hunter",
            "Description": "308 Marlin 20 Rounds Ammunition Hornady 160 Grain FTX 090255827330",
            "Brand": "Hornady",
            "Caliber": "Marlin Express",
            "Grains": 160,
            "Price": 32.86,
            "Rounds": 20,
            "Casing": "brass",
            "S/H": "4",
            "Limits": "N/A",
            "New?": "new",
            "$/round": 1.64,
            "Link": "https://ammoseek.com/share/a/45819492246"
        },
        {
            "Retailer": "SST Firearms",
            "Description": "HRNDY LVREVO 308MRLN EXPS 160GR 20RD 090255827330",
            "Brand": "Hornady",
            "Caliber": "Marlin Express",
            "Grains": 160,
            "Price": 32.99,
            "Rounds": 20,
            "Casing": "brass",
            "S/H": "8",
            "Limits": "N/A",
            "New?": "new",
            "$/round": 1.65,
            "Link": "https://ammoseek.com/share/a/282029875477"
        },
        {
            "Retailer": "Chesapeake Gunslingers",
            "Description": "Hornady LEVERevolution Rifle Ammunition .308 Marlin 160 gr FTX 2660 fps - 20/box 090255827330",
            "Brand": "Hornady",
            "Caliber": "Marlin Express",
            "Grains": 160,
            "Price": 32.99,
            "Rounds": 20,
            "Casing": "brass",
            "S/H": "9",
            "Limits": "N/A",
            "New?": "new",
            "$/round": 1.65,
            "Link": "https://ammoseek.com/share/a/279674551390"
        },
        {
            "Retailer": "GunMag Warehouse",
            "Description": "Hornady LEVERevolution .308 Marlin Express Ammo 160gr FTX 20 Rounds 090255827330",
            "Brand": "Hornady",
            "Caliber": "Marlin Express",
            "Grains": 160,
            "Price": 32.99,
            "Rounds": 20,
            "Casing": "brass",
            "S/H": "7",
            "Limits": "N/A",
            "New?": "new",
            "$/round": 1.65,
            "Link": "https://ammoseek.com/share/a/297426318796"
        },
        {
            "Retailer": "Selway Armory",
            "Description": "Hornady LEVERevolution .308 Marlin Express 160 Gr. FTX- Box of 20 090255827330",
            "Brand": "Hornady",
            "Caliber": "Marlin Express",
            "Grains": 160,
            "Price": 32.99,
            "Rounds": 20,
            "Casing": "brass",
            "S/H": "6",
            "Limits": "N/A",
            "New?": "new",
            "$/round": 1.65,
            "Link": "https://ammoseek.com/share/a/315236064256"
        },
        {
            "Retailer": "Ordnance Outpost",
            "Description": "Hrndy Lvrevo 308mrln Exps 160gr 20rd RPLH82733 090255827330",
            "Brand": "Hornady",
            "Caliber": "Marlin Express",
            "Grains": 160,
            "Price": 32.99,
            "Rounds": 20,
            "Casing": "brass",
            "S/H": "N/A",
            "Limits": "N/A",
            "New?": "new",
            "$/round": 1.65,
            "Link": "https://ammoseek.com/share/a/315143565979"
        },
        {
            "Retailer": "Armored Boar Gunworks",
            "Description": "HRNDY LVREVO 308MRLN EXPS 160GR 20RD 090255827330",
            "Brand": "Hornady",
            "Caliber": "Marlin Express",
            "Grains": 160,
            "Price": 33.0,
            "Rounds": 20,
            "Casing": "brass",
            "S/H": "8",
            "Limits": "N/A",
            "New?": "new",
            "$/round": 1.65,
            "Link": "https://ammoseek.com/share/a/298320426313"
        },
        {
            "Retailer": "Paramount Defense LLC",
            "Description": "HRNDY LVREVO 308MRLN EXPS 160GR 20RD 090255827330",
            "Brand": "Hornady",
            "Caliber": "Marlin Express",
            "Grains": 160,
            "Price": 33.0,
            "Rounds": 20,
            "Casing": "brass",
            "S/H": "8",
            "Limits": "N/A",
            "New?": "new",
            "$/round": 1.65,
            "Link": "https://ammoseek.com/share/a/311600500750"
        },
        {
            "Retailer": "USA Gun Store",
            "Description": "Hornady 82733 LEVERevolution 308 Marlin Express 160 gr Flex Tip eXpanding 20 Per Box/ 10 Cs 090255827330",
            "Brand": "Hornady",
            "Caliber": "Marlin Express",
            "Grains": 160,
            "Price": 33.0,
            "Rounds": 20,
            "Casing": "brass",
            "S/H": "9",
            "Limits": "N/A",
            "New?": "new",
            "$/round": 1.65,
            "Link": "https://ammoseek.com/share/a/258179535772"
        },
        {
            "Retailer": "Georgia Guns & Ammo",
            "Description": "HRNDY LVREVO 308MRLN EXPS 160GR 20RD 090255827330",
            "Brand": "Hornady",
            "Caliber": "Marlin Express",
            "Grains": 160,
            "Price": 33.29,
            "Rounds": 20,
            "Casing": "brass",
            "S/H": "8",
            "Limits": "N/A",
            "New?": "new",
            "$/round": 1.66,
            "Link": "https://ammoseek.com/share/a/313019905249"
        },
        {
            "Retailer": "Vizards Guns and Ammo",
            "Description": "Hornady 308 Marlin Express Ammunition 82733 160 gr Flex Tip eXpanding 20 Rounds 090255827330",
            "Brand": "Hornady",
            "Caliber": "Marlin Express",
            "Grains": 160,
            "Price": 33.57,
            "Rounds": 20,
            "Casing": "brass",
            "S/H": "8",
            "Limits": "N/A",
            "New?": "new",
            "$/round": 1.68,
            "Link": "https://ammoseek.com/share/a/280779250063"
        },
        {
            "Retailer": "Drifters Gear",
            "Description": "Hornady 82733 LEVERevolution 308 Marlin Express 160 gr Flex Tip eXpanding 20 Bx/ 10 Cs 090255827330",
            "Brand": "Hornady",
            "Caliber": "Marlin Express",
            "Grains": 160,
            "Price": 33.59,
            "Rounds": 20,
            "Casing": "brass",
            "S/H": "7",
            "Limits": "N/A",
            "New?": "new",
            "$/round": 1.68,
            "Link": "https://ammoseek.com/share/a/248066915932"
        },
        {
            "Retailer": "LG Outdoors",
            "Description": "308 Marlin 160 Grain Ballistic Tip 20 Rounds Hornady Ammunition(Price per unit for order of 10+ units)090255827330",
            "Brand": "Hornady",
            "Caliber": "Marlin Express",
            "Grains": 160,
            "Price": 33.62,
            "Rounds": 20,
            "Casing": "brass",
            "S/H": "5",
            "Limits": "N/A",
            "New?": "new",
            "$/round": 1.68,
            "Link": "https://ammoseek.com/share/a/124268748821"
        },
        {
            "Retailer": "Ammo Sale",
            "Description": "308 Marlin 160 Grain Ballistic Tip 20 Rounds Hornady Ammunition(Price per unit for order of 10+ units)090255827330",
            "Brand": "Hornady",
            "Caliber": "Marlin Express",
            "Grains": 160,
            "Price": 33.62,
            "Rounds": 20,
            "Casing": "brass",
            "S/H": "5",
            "Limits": "N/A",
            "New?": "new",
            "$/round": 1.68,
            "Link": "https://ammoseek.com/share/a/248502484378"
        },
        {
            "Retailer": "Red River Reloading",
            "Description": "Hornady LeverEvolution 308 Marlin Express 160gr FTX /20",
            "Brand": "Hornady",
            "Caliber": "Marlin Express",
            "Grains": 160,
            "Price": 33.74,
            "Rounds": 20,
            "Casing": "brass",
            "S/H": "6",
            "Limits": "N/A",
            "New?": "new",
            "$/round": 1.69,
            "Link": "https://ammoseek.com/share/a/172040887465"
        },
        {
            "Retailer": "Firearms Depot",
            "Description": "Hornady Leverevolution .308 Marlin EXP 160 Grain FTX LVREV-20 Count 090255827330",
            "Brand": "Hornady",
            "Caliber": "Marlin Express",
            "Grains": 160,
            "Price": 33.89,
            "Rounds": 20,
            "Casing": "brass",
            "S/H": "5",
            "Limits": "N/A",
            "New?": "new",
            "$/round": 1.7,
            "Link": "https://ammoseek.com/share/a/245588089087"
        },
        {
            "Retailer": "Ammo Lab",
            "Description": "Hornady 82733 LEVERevolution 308 Marlin Express 160 gr Flex Tip eXpanding 20 Bx/ 10 Cs 090255827330",
            "Brand": "Hornady",
            "Caliber": "Marlin Express",
            "Grains": 160,
            "Price": 33.94,
            "Rounds": 20,
            "Casing": "brass",
            "S/H": "8",
            "Limits": "N/A",
            "New?": "new",
            "$/round": 1.7,
            "Link": "https://ammoseek.com/share/a/250007772451"
        },
        {
            "Retailer": "SGAmmo",
            "Description": "20 Round Box - 308 Marlin Express 160 Grain FTX Hornady LeverEvolution Ammo - 82733-Free shipping on $200+",
            "Brand": "Hornady",
            "Caliber": "Marlin Express",
            "Grains": 160,
            "Price": 33.95,
            "Rounds": 20,
            "Casing": "brass",
            "S/H": "8CF",
            "Limits": "N/A",
            "New?": "new",
            "$/round": 1.7,
            "Link": "https://ammoseek.com/share/a/157698568502"
        },
        {
            "Retailer": "Adventure Gear South",
            "Description": "HRNDY LVREVO 308MRLN EXPS 160GR 20RD 090255827330",
            "Brand": "Hornady",
            "Caliber": "Marlin Express",
            "Grains": 160,
            "Price": 33.99,
            "Rounds": 20,
            "Casing": "brass",
            "S/H": "9",
            "Limits": "N/A",
            "New?": "new",
            "$/round": 1.7,
            "Link": "https://ammoseek.com/share/a/284831004928"
        },
        {
            "Retailer": "Armed In Michigan",
            "Description": "HRNDY LVREVO 308MRLN EXPS 160GR 20RD 090255827330",
            "Brand": "Hornady",
            "Caliber": "Marlin Express",
            "Grains": 160,
            "Price": 33.99,
            "Rounds": 20,
            "Casing": "brass",
            "S/H": "8",
            "Limits": "N/A",
            "New?": "new",
            "$/round": 1.7,
            "Link": "https://ammoseek.com/share/a/295256811844"
        },
        {
            "Retailer": "Hinterland Outfitters",
            "Description": "Hornady 82733 LEVERevolution 308 Marlin Express 160 gr Flex Tip eXpanding 20 Per Box/ 10 Cs 090255827330",
            "Brand": "Hornady",
            "Caliber": "Marlin Express",
            "Grains": 160,
            "Price": 34.03,
            "Rounds": 20,
            "Casing": "brass",
            "S/H": "8",
            "Limits": "N/A",
            "New?": "new",
            "$/round": 1.7,
            "Link": "https://ammoseek.com/share/a/282444589477"
        },
        {
            "Retailer": "Global Ordnance",
            "Description": "Hornady LEVERevolution Hyper Velocity Centerfire Ammunition, 308 Marlin Express, Flex Tip eXpanding, 160 Grain - 20 Cartridge Box ( 20 / 1 ) 090255827330",
            "Brand": "Hornady",
            "Caliber": "Marlin Express",
            "Grains": 160,
            "Price": 34.34,
            "Rounds": 20,
            "Casing": "brass",
            "S/H": "8",
            "Limits": "N/A",
            "New?": "new",
            "$/round": 1.72,
            "Link": "https://ammoseek.com/share/a/280740761758"
        },
        {
            "Retailer": "AmmoJoy",
            "Description": "Hornady 82733 LEVERevolution 308 Marlin Express 160 gr 2660 fps Flex Tip eXpanding (FTX) 20 Bx/10 Cs 090255827330",
            "Brand": "Hornady",
            "Caliber": "Marlin Express",
            "Grains": 160,
            "Price": 34.49,
            "Rounds": 20,
            "Casing": "brass",
            "S/H": "8",
            "Limits": "N/A",
            "New?": "new",
            "$/round": 1.73,
            "Link": "https://ammoseek.com/share/a/245062433455"
        },
        {
            "Retailer": "LG Outdoors",
            "Description": "308 Marlin 160 Grain Ballistic Tip 20 Rounds Hornady Ammunition(Price per unit for order of 10+ units)090255827330",
            "Brand": "Hornady",
            "Caliber": "Marlin Express",
            "Grains": 160,
            "Price": 34.74,
            "Rounds": 20,
            "Casing": "brass",
            "S/H": "5",
            "Limits": "N/A",
            "New?": "new",
            "$/round": 1.74,
            "Link": "https://ammoseek.com/share/a/124268748803"
        },
        {
            "Retailer": "Ammo Sale",
            "Description": "308 Marlin 160 Grain Ballistic Tip 20 Rounds Hornady Ammunition(Price per unit for order of 10+ units)090255827330",
            "Brand": "Hornady",
            "Caliber": "Marlin Express",
            "Grains": 160,
            "Price": 34.74,
            "Rounds": 20,
            "Casing": "brass",
            "S/H": "5",
            "Limits": "N/A",
            "New?": "new",
            "$/round": 1.74,
            "Link": "https://ammoseek.com/share/a/280782908344"
        },
        {
            "Retailer": "LG Outdoors",
            "Description": "308 Marlin 160 Grain Ballistic Tip 20 Rounds Hornady Ammunition(Price per unit for order of 10+ units)090255827330",
            "Brand": "Hornady",
            "Caliber": "Marlin Express",
            "Grains": 160,
            "Price": 34.84,
            "Rounds": 20,
            "Casing": "brass",
            "S/H": "5",
            "Limits": "N/A",
            "New?": "new",
            "$/round": 1.74,
            "Link": "https://ammoseek.com/share/a/125788554494"
        },
        {
            "Retailer": "Ammo Sale",
            "Description": "308 Marlin 160 Grain Ballistic Tip 20 Rounds Hornady Ammunition(Price per unit for order of 10+ units)090255827330",
            "Brand": "Hornady",
            "Caliber": "Marlin Express",
            "Grains": 160,
            "Price": 34.84,
            "Rounds": 20,
            "Casing": "brass",
            "S/H": "5",
            "Limits": "N/A",
            "New?": "new",
            "$/round": 1.74,
            "Link": "https://ammoseek.com/share/a/247757036656"
        },
        {
            "Retailer": "Midwest Gun Works",
            "Description": "Hornady Leverevolution 308 Marlin Express 160gr. FTX Ammunition 20 Round Box 090255827330",
            "Brand": "Hornady",
            "Caliber": "Marlin Express",
            "Grains": 160,
            "Price": 34.99,
            "Rounds": 20,
            "Casing": "brass",
            "S/H": "7",
            "Limits": "N/A",
            "New?": "new",
            "$/round": 1.75,
            "Link": "https://ammoseek.com/share/a/250001805766"
        },
        {
            "Retailer": "Defensive Ballistics",
            "Description": "Hornady LEVERevolution 308 Marlin Express 160gr FTX 090255827330",
            "Brand": "Hornady",
            "Caliber": "Marlin Express",
            "Grains": 160,
            "Price": 34.99,
            "Rounds": 20,
            "Casing": "brass",
            "S/H": "9",
            "Limits": "N/A",
            "New?": "new",
            "$/round": 1.75,
            "Link": "https://ammoseek.com/share/a/248502856975"
        },
        {
            "Retailer": "Outdoor Limited",
            "Description": "Hornady 308 Marlin Express Lever Evolution H82733 160 gr FTX 20 rounds 90255827330FREE SHIPPING on orders $200+",
            "Brand": "Hornady",
            "Caliber": "Marlin Express",
            "Grains": 160,
            "Price": 34.99,
            "Rounds": 20,
            "Casing": "brass",
            "S/H": "7CF",
            "Limits": "N/A",
            "New?": "new",
            "$/round": 1.75,
            "Link": "https://ammoseek.com/share/a/114321014129"
        },
        {
            "Retailer": "American Ordnance",
            "Description": "HORNADY LEVEREVOLUTION 308 Marlin Express 160GR 20RD",
            "Brand": "Hornady",
            "Caliber": "Marlin Express",
            "Grains": 160,
            "Price": 34.99,
            "Rounds": 20,
            "Casing": "brass",
            "S/H": "8",
            "Limits": "N/A",
            "New?": "new",
            "$/round": 1.75,
            "Link": "https://ammoseek.com/share/a/307012578046"
        },
        {
            "Retailer": "L&M Guns and Gear",
            "Description": "Hornady LEVERevolution Rifle Ammunition .308 Marlin 160 gr FTX 2660 fps - 20/box 090255827330",
            "Brand": "Hornady",
            "Caliber": "Marlin Express",
            "Grains": 160,
            "Price": 34.99,
            "Rounds": 20,
            "Casing": "brass",
            "S/H": "2",
            "Limits": "N/A",
            "New?": "new",
            "$/round": 1.75,
            "Link": "https://ammoseek.com/share/a/310091200582"
        },
        {
            "Retailer": "DB Firearms",
            "Description": "Hornady 82733 LEVERevolution 308 Marlin Express 160 gr Flex Tip eXpanding 20 Per Box 10 Cs 090255827330",
            "Brand": "Hornady",
            "Caliber": "Marlin Express",
            "Grains": 160,
            "Price": 34.99,
            "Rounds": 20,
            "Casing": "brass",
            "S/H": "9",
            "Limits": "N/A",
            "New?": "new",
            "$/round": 1.75,
            "Link": "https://ammoseek.com/share/a/280745280088"
        },
        {
            "Retailer": "Big Mike's Guns and Ammo",
            "Description": "HRNDY LVREVO 308MRLN EXPS 160GR 20RD 090255827330",
            "Brand": "Hornady",
            "Caliber": "Marlin Express",
            "Grains": 160,
            "Price": 35.0,
            "Rounds": 20,
            "Casing": "brass",
            "S/H": "9",
            "Limits": "N/A",
            "New?": "new",
            "$/round": 1.75,
            "Link": "https://ammoseek.com/share/a/285208211314"
        },
        {
            "Retailer": "Loftus Firearms",
            "Description": "Hornady LEVERevolution Rifle Ammunition .308 Marlin 160 gr FTX 2660 fps - 20/box 090255827330",
            "Brand": "Hornady",
            "Caliber": "Marlin Express",
            "Grains": 160,
            "Price": 35.0,
            "Rounds": 20,
            "Casing": "brass",
            "S/H": "9",
            "Limits": "N/A",
            "New?": "new",
            "$/round": 1.75,
            "Link": "https://ammoseek.com/share/a/284693827357"
        },
        {
            "Retailer": "Recoil Gunworks",
            "Description": "LeverEvolution | 308 Marlin Express | 160gr | FTX - 200rd Case 090255827330 -FREE SHIPPING",
            "Brand": "Hornady",
            "Caliber": "Marlin Express",
            "Grains": 160,
            "Price": 349.99,
            "Rounds": 200,
            "Casing": "brass",
            "S/H": "F",
            "Limits": "N/A",
            "New?": "new",
            "$/round": 1.75,
            "Link": "https://ammoseek.com/share/a/289774929925"
        },
        {
            "Retailer": "Optics Planet",
            "Description": "Hornady LEVERevolution .308 Marlin Express 160 grain Flex Tip eXpanding Brass Cased Centerfire Rifle Ammo 20 Rounds 82733 -FREE SHIPPING on $49+090255827330",
            "Brand": "Hornady",
            "Caliber": "Marlin Express",
            "Grains": 160,
            "Price": 35.09,
            "Rounds": 20,
            "Casing": "brass",
            "S/H": "8CF",
            "Limits": "N/A",
            "New?": "new",
            "$/round": 1.75,
            "Link": "https://ammoseek.com/share/a/245075485723"
        },
        {
            "Retailer": "Optics Planet",
            "Description": "Hornady LEVERevolution .308 Marlin Express 160 grain Flex Tip eXpanding Brass Cased Centerfire Rifle Ammo 200 Round -FREE SHIPPING090255827330",
            "Brand": "Hornady",
            "Caliber": "Marlin Express",
            "Grains": 160,
            "Price": 351.41,
            "Rounds": 200,
            "Casing": "brass",
            "S/H": "F",
            "Limits": "N/A",
            "New?": "new",
            "$/round": 1.76,
            "Link": "https://ammoseek.com/share/a/297465236092"
        },
        {
            "Retailer": "Shooting Surplus",
            "Description": "Hornady LEVERevolution Rifle Ammo 308 Marlin Express 160 gr Flex Tip eXpanding 20 rd 090255827330",
            "Brand": "Hornady",
            "Caliber": "Marlin Express",
            "Grains": 160,
            "Price": 35.28,
            "Rounds": 20,
            "Casing": "brass",
            "S/H": "8",
            "Limits": "N/A",
            "New?": "new",
            "$/round": 1.76,
            "Link": "https://ammoseek.com/share/a/293798980813"
        },
        {
            "Retailer": "Vizards Guns and Ammo",
            "Description": "Hornady 82733 308 Marlin Express Ammunition 160Gr Polymer Tipped 20 Rounds 090255827330",
            "Brand": "Hornady",
            "Caliber": "Marlin Express",
            "Grains": 160,
            "Price": 35.62,
            "Rounds": 20,
            "Casing": "brass",
            "S/H": "8",
            "Limits": "N/A",
            "New?": "new",
            "$/round": 1.78,
            "Link": "https://ammoseek.com/share/a/284050537588"
        },
        {
            "Retailer": "Recoil Gunworks",
            "Description": "LeverEvolution | 308 Marlin Express | 160gr | FTX - 20rd Box 090255827330 -FREE SHIPPING on $279+",
            "Brand": "Hornady",
            "Caliber": "Marlin Express",
            "Grains": 160,
            "Price": 35.99,
            "Rounds": 20,
            "Casing": "brass",
            "S/H": "7CF",
            "Limits": "N/A",
            "New?": "new",
            "$/round": 1.8,
            "Link": "https://ammoseek.com/share/a/289774929916"
        },
        {
            "Retailer": "Powder & String Outfitters",
            "Description": "Hornady 82733 LEVERevolution 308 Marlin Express 160 gr Flex Tip eXpanding 20 Bx/ 10 Cs 090255827330",
            "Brand": "Hornady",
            "Caliber": "Marlin Express",
            "Grains": 160,
            "Price": 35.99,
            "Rounds": 20,
            "Casing": "brass",
            "S/H": "6",
            "Limits": "N/A",
            "New?": "new",
            "$/round": 1.8,
            "Link": "https://ammoseek.com/share/a/276395908282"
        },
        {
            "Retailer": "Lightning Strike Arms",
            "Description": "Hornady Hornady 82733 LEVERevolution 308 Marlin Express 160... 090255827330",
            "Brand": "Hornady",
            "Caliber": "Marlin Express",
            "Grains": 160,
            "Price": 35.99,
            "Rounds": 20,
            "Casing": "brass",
            "S/H": "9",
            "Limits": "N/A",
            "New?": "new",
            "$/round": 1.8,
            "Link": "https://ammoseek.com/share/a/280758913144"
        },
        {
            "Retailer": "Brownells",
            "Description": "308 MARLIN EXPRESS 160GR FLEX TIP EXPANDING 20/BOX",
            "Brand": "Hornady",
            "Caliber": "Marlin Express",
            "Grains": 160,
            "Price": 35.99,
            "Rounds": 20,
            "Casing": "brass",
            "S/H": "8",
            "Limits": "N/A",
            "New?": "new",
            "$/round": 1.8,
            "Link": "https://ammoseek.com/share/a/291550137280"
        },
        {
            "Retailer": "Netti Ammo",
            "Description": "HRNDY LVREVO 308MRLN EXPS 160GR 20RD 090255827330",
            "Brand": "Hornady",
            "Caliber": "Marlin Express",
            "Grains": 160,
            "Price": 36.0,
            "Rounds": 20,
            "Casing": "brass",
            "S/H": "9",
            "Limits": "N/A",
            "New?": "new",
            "$/round": 1.8,
            "Link": "https://ammoseek.com/share/a/279674542060"
        },
        {
            "Retailer": "Snyder Shooting Supply",
            "Description": "HRNDY LVREVO 308MRLN EXPS 160GR 20RD 090255827330",
            "Brand": "Hornady",
            "Caliber": "Marlin Express",
            "Grains": 160,
            "Price": 36.0,
            "Rounds": 20,
            "Casing": "brass",
            "S/H": "8",
            "Limits": "N/A",
            "New?": "new",
            "$/round": 1.8,
            "Link": "https://ammoseek.com/share/a/312669016708"
        },
        {
            "Retailer": "Impact Guns",
            "Description": "Hornady LEVERevolution .308 Marlin Express 160gr, Evolution Bullet 20rd Box 090255827330",
            "Brand": "Hornady",
            "Caliber": "Marlin Express",
            "Grains": 160,
            "Price": 36.09,
            "Rounds": 20,
            "Casing": "brass",
            "S/H": "7",
            "Limits": "N/A",
            "New?": "new",
            "$/round": 1.8,
            "Link": "https://ammoseek.com/share/a/157487521127"
        },
        {
            "Retailer": "GunBuyer",
            "Description": "Hornady LEVERevolution 308 Marlin Express 160 Grains FTX 20 Round Box 82733 090255827330",
            "Brand": "Hornady",
            "Caliber": "Marlin Express",
            "Grains": 160,
            "Price": 36.38,
            "Rounds": 20,
            "Casing": "brass",
            "S/H": "4",
            "Limits": "N/A",
            "New?": "new",
            "$/round": 1.82,
            "Link": "https://ammoseek.com/share/a/123363603011"
        },
        {
            "Retailer": "KIR Ammo",
            "Description": "Hornady Leverevolution .308 Marlin Express 160 Grain FTX - 20 Rounds (Box) 82733FREE SHIPPING OVER $199",
            "Brand": "Hornady",
            "Caliber": "Marlin Express",
            "Grains": 160,
            "Price": 36.95,
            "Rounds": 20,
            "Casing": "brass",
            "S/H": "9CF",
            "Limits": "N/A",
            "New?": "new",
            "$/round": 1.85,
            "Link": "https://ammoseek.com/share/a/244323557776"
        },
        {
            "Retailer": "76 Rounds",
            "Description": "Hornady LEVERevolution Rifle Ammunition .308 Marlin 160 gr FTX 2660 fps - 20/box 090255827330",
            "Brand": "Hornady",
            "Caliber": "Marlin Express",
            "Grains": 160,
            "Price": 36.99,
            "Rounds": 20,
            "Casing": "brass",
            "S/H": "7",
            "Limits": "N/A",
            "New?": "new",
            "$/round": 1.85,
            "Link": "https://ammoseek.com/share/a/297967358989"
        },
        {
            "Retailer": "We Kick Brass",
            "Description": "Hornady Hornady, LeverEvolution, 308 Marlin Express, 160 Grain, FlexTip, 20 Round Box 090255827330 -$15.95 flat rate shipping / FREE SHIPPING over $300",
            "Brand": "Hornady",
            "Caliber": "Marlin Express",
            "Grains": 160,
            "Price": 36.99,
            "Rounds": 20,
            "Casing": "brass",
            "S/H": "8CF",
            "Limits": "N/A",
            "New?": "new",
            "$/round": 1.85,
            "Link": "https://ammoseek.com/share/a/315366161932"
        },
        {
            "Retailer": "Palmetto State Armory",
            "Description": "Hornady 308 Marlin Express 160 gr FTX LEVERevolution 20 Rounds Ammunition - 82733 090255827330",
            "Brand": "Hornady",
            "Caliber": "Marlin Express",
            "Grains": 160,
            "Price": 36.99,
            "Rounds": 20,
            "Casing": "brass",
            "S/H": "5",
            "Limits": "N/A",
            "New?": "new",
            "$/round": 1.85,
            "Link": "https://ammoseek.com/share/a/183398117062"
        },
        {
            "Retailer": "White Birch Armory",
            "Description": "Hornady 82733 LEVERevolution 308 Marlin Express 160 gr Flex Tip eXpanding 20 Bx/ 10 Cs 090255827330",
            "Brand": "Hornady",
            "Caliber": "Marlin Express",
            "Grains": 160,
            "Price": 37.04,
            "Rounds": 20,
            "Casing": "brass",
            "S/H": "7",
            "Limits": "N/A",
            "New?": "new",
            "$/round": 1.85,
            "Link": "https://ammoseek.com/share/a/105656357528"
        },
        {
            "Retailer": "LG Outdoors",
            "Description": "308 Marlin 160 Grain Ballistic Tip 20 Rounds Hornady Ammunition(Price per unit for order of 10+ units)090255827330",
            "Brand": "Hornady",
            "Caliber": "Marlin Express",
            "Grains": 160,
            "Price": 37.26,
            "Rounds": 20,
            "Casing": "brass",
            "S/H": "5",
            "Limits": "N/A",
            "New?": "new",
            "$/round": 1.86,
            "Link": "https://ammoseek.com/share/a/124268748809"
        },
        {
            "Retailer": "Ammo Sale",
            "Description": "308 Marlin 160 Grain Ballistic Tip 20 Rounds Hornady Ammunition(Price per unit for order of 10+ units)090255827330",
            "Brand": "Hornady",
            "Caliber": "Marlin Express",
            "Grains": 160,
            "Price": 37.26,
            "Rounds": 20,
            "Casing": "brass",
            "S/H": "5",
            "Limits": "N/A",
            "New?": "new",
            "$/round": 1.86,
            "Link": "https://ammoseek.com/share/a/246353816422"
        },
        {
            "Retailer": "Botach",
            "Description": "Hornady LeveRevolution .308 Marlin Express Ammo 160gr 20-Round 090255827330",
            "Brand": "Hornady",
            "Caliber": "Marlin Express",
            "Grains": 160,
            "Price": 37.49,
            "Rounds": 20,
            "Casing": "brass",
            "S/H": "6",
            "Limits": "N/A",
            "New?": "new",
            "$/round": 1.88,
            "Link": "https://ammoseek.com/share/a/299189703409"
        },
        {
            "Retailer": "Guns.com",
            "Description": "HORNADY LEVEREVOLUTION 090255827330",
            "Brand": "Hornady",
            "Caliber": "Marlin Express",
            "Grains": 160,
            "Price": 37.99,
            "Rounds": 20,
            "Casing": "brass",
            "S/H": "9",
            "Limits": "N/A",
            "New?": "new",
            "$/round": 1.9,
            "Link": "https://ammoseek.com/share/a/294523061587"
        },
        {
            "Retailer": "Palmetto State Armory",
            "Description": "Winchester 308 150gr Deer Season XP Ammunition, 20 Round Box - X308DS 020892221550",
            "Brand": "Winchester",
            "Caliber": "Marlin Express",
            "Grains": 150,
            "Price": 37.99,
            "Rounds": 20,
            "Casing": "brass",
            "S/H": "5",
            "Limits": "N/A",
            "New?": "new",
            "$/round": 1.9,
            "Link": "https://ammoseek.com/share/a/181266956512"
        },
        {
            "Retailer": "Midsouth Shooters Supply",
            "Description": "Hornady 308 Marlin Express 160 Grain LEVERevolution Ballistic 20 Rounds",
            "Brand": "Hornady",
            "Caliber": "Marlin Express",
            "Grains": 160,
            "Price": 37.99,
            "Rounds": 20,
            "Casing": "brass",
            "S/H": "7",
            "Limits": "N/A",
            "New?": "new",
            "$/round": 1.9,
            "Link": "https://ammoseek.com/share/a/4294982876"
        },
        {
            "Retailer": "Ammunition Depot",
            "Description": "Hornady Leverevolution 308 Marlin Express 160 Gr Flex Tip eXpanding (20 Rounds) 090255827330FREE SHIPPING on orders over $149",
            "Brand": "Hornady",
            "Caliber": "Marlin Express",
            "Grains": 160,
            "Price": 38.49,
            "Rounds": 20,
            "Casing": "brass",
            "S/H": "8CF",
            "Limits": "N/A",
            "New?": "new",
            "$/round": 1.93,
            "Link": "https://ammoseek.com/share/a/282166639855"
        },
        {
            "Retailer": "CME Firearms",
            "Description": "Hornady 82733 LEVERevolution 308 Marlin Express 160 gr Flex Tip eXpanding 20 Bx/ 10 Cs 090255827330",
            "Brand": "Hornady",
            "Caliber": "Marlin Express",
            "Grains": 160,
            "Price": 38.59,
            "Rounds": 20,
            "Casing": "brass",
            "S/H": "9",
            "Limits": "N/A",
            "New?": "new",
            "$/round": 1.93,
            "Link": "https://ammoseek.com/share/a/304265718559"
        },
        {
            "Retailer": "Maryland Munitions",
            "Description": "HORNADY LEVEREVOLUTION 308 MARLIN EXPRESS 160GR FTX 20RD BOX 090255827330FREE SHIPPING on orders over $250",
            "Brand": "Hornady",
            "Caliber": "Marlin Express",
            "Grains": 160,
            "Price": 38.63,
            "Rounds": 20,
            "Casing": "brass",
            "S/H": "9CF",
            "Limits": "N/A",
            "New?": "new",
            "$/round": 1.93,
            "Link": "https://ammoseek.com/share/a/294957714616"
        },
        {
            "Retailer": "Cape Gun Works",
            "Description": "Hornady 82733 LEVERevolution 308 Marlin Express 160 gr Flex Tip eXpanding 20 Round Box 090255827330",
            "Brand": "Hornady",
            "Caliber": "Marlin Express",
            "Grains": 160,
            "Price": 38.99,
            "Rounds": 20,
            "Casing": "brass",
            "S/H": "6",
            "Limits": "N/A",
            "New?": "new",
            "$/round": 1.95,
            "Link": "https://ammoseek.com/share/a/261355026883"
        },
        {
            "Retailer": "LeadFeather Guns & Ammo",
            "Description": "Hornady 82733 LEVERevolution 308 Marlin Express 160 gr Flex Tip eXpanding 20 Bx/ 10 Cs 090255827330",
            "Brand": "Hornady",
            "Caliber": "Marlin Express",
            "Grains": 160,
            "Price": 38.99,
            "Rounds": 20,
            "Casing": "brass",
            "S/H": "5",
            "Limits": "N/A",
            "New?": "new",
            "$/round": 1.95,
            "Link": "https://ammoseek.com/share/a/278896991716"
        },
        {
            "Retailer": "Target Sports USA",
            "Description": "Hornady LeveRevolution 308 Marlin Express Ammo 160 Grain FTX Case of 200 (10 Boxes of 20)- FREE SHIPPING- brass case - MPN 82733 ( UPC - 090255827330)",
            "Brand": "Hornady",
            "Caliber": "Marlin Express",
            "Grains": 160,
            "Price": 399.9,
            "Rounds": 200,
            "Casing": "brass",
            "S/H": "F",
            "Limits": "N/A",
            "New?": "new",
            "$/round": 2.0,
            "Link": "https://ammoseek.com/share/a/245819333065"
        },
        {
            "Retailer": "SCHEELS",
            "Description": "Hornady LEVERevolution FTX 308 Marlin Express Rifle Ammunition 20 Round Box 090255827330",
            "Brand": "Hornady",
            "Caliber": "Marlin Express",
            "Grains": 160,
            "Price": 39.99,
            "Rounds": 20,
            "Casing": "brass",
            "S/H": "9",
            "Limits": "N/A",
            "New?": "new",
            "$/round": 2.0,
            "Link": "https://ammoseek.com/share/a/296069328637"
        },
        {
            "Retailer": "Target Sports USA",
            "Description": "Hornady LeveRevolution 308 Marlin Express Ammo 160 Grain FTX Box of 20 - brass case - MPN 82733 ( UPC - 090255827330)",
            "Brand": "Hornady",
            "Caliber": "Marlin Express",
            "Grains": 160,
            "Price": 39.99,
            "Rounds": 20,
            "Casing": "brass",
            "S/H": "8",
            "Limits": "N/A",
            "New?": "new",
            "$/round": 2.0,
            "Link": "https://ammoseek.com/share/a/245819333065"
        },
        {
            "Retailer": "ZERT Nation",
            "Description": "Hornady LEVERevolution .308 Marlin Express 160 gr Flex Tip eXpanding 20 Per Box 090255827330FREE SHIPPING on orders $150+",
            "Brand": "Hornady",
            "Caliber": "Marlin Express",
            "Grains": 160,
            "Price": 39.99,
            "Rounds": 20,
            "Casing": "brass",
            "S/H": "9CF",
            "Limits": "N/A",
            "New?": "new",
            "$/round": 2.0,
            "Link": "https://ammoseek.com/share/a/293355341548"
        },
        {
            "Retailer": "Green Top",
            "Description": "Hornady LEVERevolution .308 Marlin Express 160 Gr Flex Tip Expanding - FREE SHIPPING Over $100 Under 50Lbs 090255827330",
            "Brand": "Hornady",
            "Caliber": "Marlin Express",
            "Grains": 160,
            "Price": 40.99,
            "Rounds": 20,
            "Casing": "brass",
            "S/H": "6CF",
            "Limits": "N/A",
            "New?": "new",
            "$/round": 2.05,
            "Link": "https://ammoseek.com/share/a/280805786665"
        },
        {
            "Retailer": "Natchez Shooting & Outdoors",
            "Description": "Hornady LEVERevolution Rifle Ammunition .308 Marlin 160 gr FTX 2660 fps - 20/box 090255827330",
            "Brand": "Hornady",
            "Caliber": "Marlin Express",
            "Grains": 160,
            "Price": 41.49,
            "Rounds": 20,
            "Casing": "brass",
            "S/H": "5",
            "Limits": "N/A",
            "New?": "new",
            "$/round": 2.08,
            "Link": "https://ammoseek.com/share/a/244745630866"
        },
        {
            "Retailer": "Native Outdoors Ammunition",
            "Description": "Hornady .308 Marlin Express 160 GR FTX LEVERevolution - 20 Rounds HOR82733 090255827330",
            "Brand": "Hornady",
            "Caliber": "Marlin Express",
            "Grains": 160,
            "Price": 41.99,
            "Rounds": 20,
            "Casing": "brass",
            "S/H": "8",
            "Limits": "N/A",
            "New?": "new",
            "$/round": 2.1,
            "Link": "https://ammoseek.com/share/a/246572873755"
        },
        {
            "Retailer": "Mack's Prairie Wings",
            "Description": "Hornady 308 Marlin EXP 160 Gr Leverevolution FTXFREE SHIPPING on $100+",
            "Brand": "Hornady",
            "Caliber": "Marlin Express",
            "Grains": 160,
            "Price": 42.99,
            "Rounds": 20,
            "Casing": "brass",
            "S/H": "9CF",
            "Limits": "N/A",
            "New?": "new",
            "$/round": 2.15,
            "Link": "https://ammoseek.com/share/a/282103724437"
        },
        {
            "Retailer": "Bass Pro Shops",
            "Description": "Hornady LEVERevolution .308 Marlin Express 160 Grain Flex Tip Centerfire Rifle Ammo 090255827330",
            "Brand": "Hornady",
            "Caliber": "Marlin Express",
            "Grains": 160,
            "Price": 42.99,
            "Rounds": 20,
            "Casing": "brass",
            "S/H": "9",
            "Limits": "N/A",
            "New?": "new",
            "$/round": 2.15,
            "Link": "https://ammoseek.com/share/a/247489325098"
        },
        {
            "Retailer": "Cabela's",
            "Description": "Hornady LEVERevolution .308 Marlin Express 160 Grain Flex Tip Centerfire Rifle Ammo 090255827330",
            "Brand": "Hornady",
            "Caliber": "Marlin Express",
            "Grains": 160,
            "Price": 42.99,
            "Rounds": 20,
            "Casing": "brass",
            "S/H": "8",
            "Limits": "N/A",
            "New?": "new",
            "$/round": 2.15,
            "Link": "https://ammoseek.com/share/a/247489336306"
        },
        {
            "Retailer": "MidwayUSA",
            "Description": "Hornady LEVERevolution 308 Marlin Express Ammo 160 Grain Hornady FTX Polymer Tip Box of 20 090255827330",
            "Brand": "Hornady",
            "Caliber": "Marlin Express",
            "Grains": 160,
            "Price": 45.99,
            "Rounds": 20,
            "Casing": "brass",
            "S/H": "8",
            "Limits": "N/A",
            "New?": "new",
            "$/round": 2.3,
            "Link": "https://ammoseek.com/share/a/280102590619"
        }
    ]
}